Workbook

Sheet Project Instructions
A1: PR. 2 Analyzer
A2: Topics: - Conditional Formatting - WHAT IF Analysis - Linear Regression (Using Data Analysis Toolpak) - Data Analysis Feature (Descriptive Stats, Regression, Histogram) - Data Storytelling - Add Symbols or Arrows in Custom Formatting - Create Timestamp - Find High-Value Customers using Groupby(), index(), and match() combination - Advanced Descriptive Analytics - Pivot Table with Dashboard - Creating bar charts - Creating line charts - Creating pie charts Main Tasks: 1. Apply conditional formatting to highlight top 10 customers based on total purchase. 2. Perform WHAT IF Analysis to see impact of changing discount on total profit. 3. Use Data Analysis Toolpak to run Linear Regression (Profit vs Sales). 4. Use 'Descriptive Statistics' from Analysis Toolpak on the dataset. 5. Add up/down arrows on monthly sales growth. 6. Create a timestamp column using NOW(). 7. Identify high-value customers using index(), match(), and filters. 8. Create Pivot Table to analyze total sales by region and product. 9. Create bar, line, and pie charts to visualize KPIs. 10. Summarize insights using a dashboard. Deliverable: Complete the given worksheet by applying the required formulas in respective sheets.

Sheet Dataset
A1: Customer_ID | B1: Customer_Name | C1: Region | D1: Product_Category | E1: Sales | F1: Quantity | G1: Discount | H1: Order_Date | I1: Profit | J1: Customer Total Purchase | K1: Top 10 Customer | L1: Gross Sales (pre-discount) | M1: Scenario Sales | N1: Scenario Profit | O1: Profit Margin % | P1: Order Month | Q1: Customer Tier | R1: Report Timestamp | T1: WHAT-IF ANALYSIS – DISCOUNT vs TOTAL PROFIT | AA1: JUMP TO (click)
A2: CUST019 | B2: James Davis | C2: West | D2: Books | E2: 1036.09 | F2: 4 | G2: 0.2 | H2: 45392 | I2: 331.55 | J2: =SUMIFS($E$2:$E$201,$A$2:$A$201,A2) -> 4640.11 | K2: =IF(INDEX('Pivot Table'!$N$5:$N$34,MATCH(A2,'Pivot Table'!$I$5:$I$34,0))<=10,"Top 10","") | L2: =ROUND(E2/(1-G2),2) -> 1295.11 | M2: =ROUND(L2*(1-$U$3),2) -> 1165.6 | N2: =ROUND(M2-(E2-I2),2) -> 461.06 | O2: =I2/E2 -> 0.32000116 | P2: =DATE(YEAR(H2),MONTH(H2),1) -> 45383 | Q2: =IF(J2>='Pivot Table'!$R$4,"High Value","Standard") -> Standard | R2: =NOW() -> 46304.64
A3: CUST012 | B3: Robert Anderson | C3: West | D3: Clothing | E3: 1101.28 | F3: 3 | G3: 0.2 | H3: 45393 | I3: 440.51 | J3: =SUMIFS($E$2:$E$201,$A$2:$A$201,A3) -> 8339 | K3: =IF(INDEX('Pivot Table'!$N$5:$N$34,MATCH(A3,'Pivot Table'!$I$5:$I$34,0))<=10,"Top 10","") -> Top 10 | L3: =ROUND(E3/(1-G3),2) -> 1376.6 | M3: =ROUND(L3*(1-$U$3),2) -> 1238.94 | N3: =ROUND(M3-(E3-I3),2) -> 578.17 | O3: =I3/E3 -> 0.39999818 | P3: =DATE(YEAR(H3),MONTH(H3),1) -> 45383 | Q3: =IF(J3>='Pivot Table'!$R$4,"High Value","Standard") -> High Value | R3: =NOW() -> 46304.64 | T3: Scenario discount (enter) | U3: 0.1 | AA3: 1. What-If Analysis
A4: CUST017 | B4: James Taylor | C4: East | D4: Books | E4: 713.34 | F4: 17 | G4: 0 | H4: 45396 | I4: 285.34 | J4: =SUMIFS($E$2:$E$201,$A$2:$A$201,A4) -> 3419.2 | K4: =IF(INDEX('Pivot Table'!$N$5:$N$34,MATCH(A4,'Pivot Table'!$I$5:$I$34,0))<=10,"Top 10","") | L4: =ROUND(E4/(1-G4),2) -> 713.34 | M4: =ROUND(L4*(1-$U$3),2) -> 642.01 | N4: =ROUND(M4-(E4-I4),2) -> 214.01 | O4: =I4/E4 -> 0.40000561 | P4: =DATE(YEAR(H4),MONTH(H4),1) -> 45383 | Q4: =IF(J4>='Pivot Table'!$R$4,"High Value","Standard") -> Standard | R4: =NOW() -> 46304.64 | T4: Metric | U4: Current | V4: Scenario | W4: Change | X4: % Change | AA4: 2. Descriptive Statistics
A5: CUST005 | B5: Robert Anderson | C5: South | D5: Electronics | E5: 760.93 | F5: 4 | G5: 0.15 | H5: 45396 | I5: 161.7 | J5: =SUMIFS($E$2:$E$201,$A$2:$A$201,A5) -> 6666.13 | K5: =IF(INDEX('Pivot Table'!$N$5:$N$34,MATCH(A5,'Pivot Table'!$I$5:$I$34,0))<=10,"Top 10","") | L5: =ROUND(E5/(1-G5),2) -> 895.21 | M5: =ROUND(L5*(1-$U$3),2) -> 805.69 | N5: =ROUND(M5-(E5-I5),2) -> 206.46 | O5: =I5/E5 -> 0.21250312 | P5: =DATE(YEAR(H5),MONTH(H5),1) -> 45383 | Q5: =IF(J5>='Pivot Table'!$R$4,"High Value","Standard") -> Standard | R5: =NOW() -> 46304.64 | T5: Average discount | U5: =AVERAGE($G$2:$G$201) -> 0.09725 | V5: =U3 -> 0.1 | W5: =V5-U5 -> 0.00275 | AA5: 3. Regression (ToolPak format)
A6: CUST030 | B6: James Wilson | C6: North | D6: Books | E6: 847 | F6: 12 | G6: 0.2 | H6: 45397 | I6: 271.04 | J6: =SUMIFS($E$2:$E$201,$A$2:$A$201,A6) -> 7928.71 | K6: =IF(INDEX('Pivot Table'!$N$5:$N$34,MATCH(A6,'Pivot Table'!$I$5:$I$34,0))<=10,"Top 10","") -> Top 10 | L6: =ROUND(E6/(1-G6),2) -> 1058.75 | M6: =ROUND(L6*(1-$U$3),2) -> 952.88 | N6: =ROUND(M6-(E6-I6),2) -> 376.92 | O6: =I6/E6 -> 0.32 | P6: =DATE(YEAR(H6),MONTH(H6),1) -> 45383 | Q6: =IF(J6>='Pivot Table'!$R$4,"High Value","Standard") -> Standard | R6: =NOW() -> 46304.64 | T6: Total sales | U6: =SUM($E$2:$E$201) -> 195217.76 | V6: =SUM(M2:M201) -> 196224.59 | W6: =V6-U6 -> 1006.83 | X6: =W6/U6 -> 0.0051574713 | AA6: 4. Residual Output
A7: CUST007 | B7: Michael Anderson | C7: North | D7: Furniture | E7: 965.64 | F7: 8 | G7: 0.1 | H7: 45398 | I7: 304.18 | J7: =SUMIFS($E$2:$E$201,$A$2:$A$201,A7) -> 9941.88 | K7: =IF(INDEX('Pivot Table'!$N$5:$N$34,MATCH(A7,'Pivot Table'!$I$5:$I$34,0))<=10,"Top 10","") -> Top 10 | L7: =ROUND(E7/(1-G7),2) -> 1072.93 | M7: =ROUND(L7*(1-$U$3),2) -> 965.64 | N7: =ROUND(M7-(E7-I7),2) -> 304.18 | O7: =I7/E7 -> 0.31500352 | P7: =DATE(YEAR(H7),MONTH(H7),1) -> 45383 | Q7: =IF(J7>='Pivot Table'!$R$4,"High Value","Standard") -> High Value | R7: =NOW() -> 46304.64 | T7: Total cost (held constant) | U7: =SUM($E$2:$E$201)-SUM($I$2:$I$201) -> 126930.75 | V7: =U7 -> 126930.75 | W7: =V7-U7 -> 0 | X7: =IF(U7=0,0,W7/U7) -> 0 | AA7: 5. Histogram
A8: CUST001 | B8: Linda Wilson | C8: West | D8: Electronics | E8: 1317.53 | F8: 12 | G8: 0.05 | H8: 45398 | I8: 312.91 | J8: =SUMIFS($E$2:$E$201,$A$2:$A$201,A8) -> 6549.55 | K8: =IF(INDEX('Pivot Table'!$N$5:$N$34,MATCH(A8,'Pivot Table'!$I$5:$I$34,0))<=10,"Top 10","") | L8: =ROUND(E8/(1-G8),2) -> 1386.87 | M8: =ROUND(L8*(1-$U$3),2) -> 1248.18 | N8: =ROUND(M8-(E8-I8),2) -> 243.56 | O8: =I8/E8 -> 0.23749744 | P8: =DATE(YEAR(H8),MONTH(H8),1) -> 45383 | Q8: =IF(J8>='Pivot Table'!$R$4,"High Value","Standard") -> Standard | R8: =NOW() -> 46304.64 | T8: TOTAL PROFIT | U8: =SUM($I$2:$I$201) -> 68287.01 | V8: =SUM(N2:N201) -> 69293.84 | W8: =V8-U8 -> 1006.83 | X8: =W8/U8 -> 0.014744093
A9: CUST026 | B9: Mary Davis | C9: East | D9: Furniture | E9: 1074.47 | F9: 6 | G9: 0.2 | H9: 45401 | I9: 300.85 | J9: =SUMIFS($E$2:$E$201,$A$2:$A$201,A9) -> 9371.81 | K9: =IF(INDEX('Pivot Table'!$N$5:$N$34,MATCH(A9,'Pivot Table'!$I$5:$I$34,0))<=10,"Top 10","") -> Top 10 | L9: =ROUND(E9/(1-G9),2) -> 1343.09 | M9: =ROUND(L9*(1-$U$3),2) -> 1208.78 | N9: =ROUND(M9-(E9-I9),2) -> 435.16 | O9: =I9/E9 -> 0.27999851 | P9: =DATE(YEAR(H9),MONTH(H9),1) -> 45383 | Q9: =IF(J9>='Pivot Table'!$R$4,"High Value","Standard") -> High Value | R9: =NOW() -> 46304.64 | T9: Profit margin | U9: =U8/U6 -> 0.34979917 | V9: =V8/V6 -> 0.35313535 | W9: =V9-U9 -> 0.0033361859
A10: CUST009 | B10: Linda Jackson | C10: Central | D10: Books | E10: 501.54 | F10: 11 | G10: 0.05 | H10: 45401 | I10: 190.59 | J10: =SUMIFS($E$2:$E$201,$A$2:$A$201,A10) -> 6505.2 | K10: =IF(INDEX('Pivot Table'!$N$5:$N$34,MATCH(A10,'Pivot Table'!$I$5:$I$34,0))<=10,"Top 10","") | L10: =ROUND(E10/(1-G10),2) -> 527.94 | M10: =ROUND(L10*(1-$U$3),2) -> 475.15 | N10: =ROUND(M10-(E10-I10),2) -> 164.2 | O10: =I10/E10 -> 0.38000957 | P10: =DATE(YEAR(H10),MONTH(H10),1) -> 45383 | Q10: =IF(J10>='Pivot Table'!$R$4,"High Value","Standard") -> Standard | R10: =NOW() -> 46304.64
A11: CUST010 | B11: David Thomas | C11: Central | D11: Clothing | E11: 737.31 | F11: 2 | G11: 0.05 | H11: 45401 | I11: 350.22 | J11: =SUMIFS($E$2:$E$201,$A$2:$A$201,A11) -> 4259.22 | K11: =IF(INDEX('Pivot Table'!$N$5:$N$34,MATCH(A11,'Pivot Table'!$I$5:$I$34,0))<=10,"Top 10","") | L11: =ROUND(E11/(1-G11),2) -> 776.12 | M11: =ROUND(L11*(1-$U$3),2) -> 698.51 | N11: =ROUND(M11-(E11-I11),2) -> 311.42 | O11: =I11/E11 -> 0.47499695 | P11: =DATE(YEAR(H11),MONTH(H11),1) -> 45383 | Q11: =IF(J11>='Pivot Table'!$R$4,"High Value","Standard") -> Standard | R11: =NOW() -> 46304.64 | T11: Target total profit (enter) | U11: 80000
A12: CUST014 | B12: Emma Davis | C12: West | D12: Office Supplies | E12: 1572.82 | F12: 6 | G12: 0.05 | H12: 45402 | I12: 672.38 | J12: =SUMIFS($E$2:$E$201,$A$2:$A$201,A12) -> 6729.89 | K12: =IF(INDEX('Pivot Table'!$N$5:$N$34,MATCH(A12,'Pivot Table'!$I$5:$I$34,0))<=10,"Top 10","") | L12: =ROUND(E12/(1-G12),2) -> 1655.6 | M12: =ROUND(L12*(1-$U$3),2) -> 1490.04 | N12: =ROUND(M12-(E12-I12),2) -> 589.6 | O12: =I12/E12 -> 0.42749965 | P12: =DATE(YEAR(H12),MONTH(H12),1) -> 45383 | Q12: =IF(J12>='Pivot Table'!$R$4,"High Value","Standard") -> Standard | R12: =NOW() -> 46304.64 | T12: Discount needed to hit target (Goal Seek) | U12: =IF(1-(U11+U7)/SUM(L2:L201)<0,"Not achievable",1-(U11+U7)/SUM(L2:L201)) -> 0.050895058
A13: CUST014 | B13: David Thomas | C13: Central | D13: Books | E13: 1343.13 | F13: 14 | G13: 0.15 | H13: 45404 | I13: 456.66 | J13: =SUMIFS($E$2:$E$201,$A$2:$A$201,A13) -> 6729.89 | K13: =IF(INDEX('Pivot Table'!$N$5:$N$34,MATCH(A13,'Pivot Table'!$I$5:$I$34,0))<=10,"Top 10","") | L13: =ROUND(E13/(1-G13),2) -> 1580.15 | M13: =ROUND(L13*(1-$U$3),2) -> 1422.14 | N13: =ROUND(M13-(E13-I13),2) -> 535.67 | O13: =I13/E13 -> 0.33999687 | P13: =DATE(YEAR(H13),MONTH(H13),1) -> 45383 | Q13: =IF(J13>='Pivot Table'!$R$4,"High Value","Standard") -> Standard | R13: =NOW() -> 46304.64
A14: CUST007 | B14: Michael Anderson | C14: Central | D14: Books | E14: 1191.58 | F14: 14 | G14: 0.05 | H14: 45406 | I14: 452.8 | J14: =SUMIFS($E$2:$E$201,$A$2:$A$201,A14) -> 9941.88 | K14: =IF(INDEX('Pivot Table'!$N$5:$N$34,MATCH(A14,'Pivot Table'!$I$5:$I$34,0))<=10,"Top 10","") -> Top 10 | L14: =ROUND(E14/(1-G14),2) -> 1254.29 | M14: =ROUND(L14*(1-$U$3),2) -> 1128.86 | N14: =ROUND(M14-(E14-I14),2) -> 390.08 | O14: =I14/E14 -> 0.37999966 | P14: =DATE(YEAR(H14),MONTH(H14),1) -> 45383 | Q14: =IF(J14>='Pivot Table'!$R$4,"High Value","Standard") -> High Value | R14: =NOW() -> 46304.64 | T14: SENSITIVITY TABLE – impact of changing the discount
A15: CUST023 | B15: Robert Anderson | C15: West | D15: Furniture | E15: 822.28 | F15: 7 | G15: 0.05 | H15: 45406 | I15: 273.41 | J15: =SUMIFS($E$2:$E$201,$A$2:$A$201,A15) -> 5913.68 | K15: =IF(INDEX('Pivot Table'!$N$5:$N$34,MATCH(A15,'Pivot Table'!$I$5:$I$34,0))<=10,"Top 10","") | L15: =ROUND(E15/(1-G15),2) -> 865.56 | M15: =ROUND(L15*(1-$U$3),2) -> 779 | N15: =ROUND(M15-(E15-I15),2) -> 230.13 | O15: =I15/E15 -> 0.33250231 | P15: =DATE(YEAR(H15),MONTH(H15),1) -> 45383 | Q15: =IF(J15>='Pivot Table'!$R$4,"High Value","Standard") -> Standard | R15: =NOW() -> 46304.64 | T15: Discount | U15: Total Sales | V15: Total Profit | W15: Profit Margin | X15: Δ Profit vs Current | Y15: % Δ Profit
A16: CUST029 | B16: David Smith | C16: North | D16: Furniture | E16: 521.67 | F16: 15 | G16: 0.15 | H16: 45409 | I16: 155.2 | J16: =SUMIFS($E$2:$E$201,$A$2:$A$201,A16) -> 5779.05 | K16: =IF(INDEX('Pivot Table'!$N$5:$N$34,MATCH(A16,'Pivot Table'!$I$5:$I$34,0))<=10,"Top 10","") | L16: =ROUND(E16/(1-G16),2) -> 613.73 | M16: =ROUND(L16*(1-$U$3),2) -> 552.36 | N16: =ROUND(M16-(E16-I16),2) -> 185.89 | O16: =I16/E16 -> 0.29750609 | P16: =DATE(YEAR(H16),MONTH(H16),1) -> 45383 | Q16: =IF(J16>='Pivot Table'!$R$4,"High Value","Standard") -> Standard | R16: =NOW() -> 46304.64 | T16: 0 | U16: =SUM($L$2:$L$201)*(1-T16) -> 218027.26 | V16: =U16-$U$7 -> 91096.51 | W16: =V16/U16 -> 0.41782165 | X16: =V16-$U$8 -> 22809.5 | Y16: =X16/$U$8 -> 0.334024
A17: CUST005 | B17: Sarah Anderson | C17: South | D17: Electronics | E17: 1502.93 | F17: 14 | G17: 0.2 | H17: 45410 | I17: 300.59 | J17: =SUMIFS($E$2:$E$201,$A$2:$A$201,A17) -> 6666.13 | K17: =IF(INDEX('Pivot Table'!$N$5:$N$34,MATCH(A17,'Pivot Table'!$I$5:$I$34,0))<=10,"Top 10","") | L17: =ROUND(E17/(1-G17),2) -> 1878.66 | M17: =ROUND(L17*(1-$U$3),2) -> 1690.79 | N17: =ROUND(M17-(E17-I17),2) -> 488.45 | O17: =I17/E17 -> 0.20000266 | P17: =DATE(YEAR(H17),MONTH(H17),1) -> 45383 | Q17: =IF(J17>='Pivot Table'!$R$4,"High Value","Standard") -> Standard | R17: =NOW() -> 46304.64 | T17: 0.05 | U17: =SUM($L$2:$L$201)*(1-T17) -> 207125.9 | V17: =U17-$U$7 -> 80195.147 | W17: =V17/U17 -> 0.38718069 | X17: =V17-$U$8 -> 11908.137 | Y17: =X17/$U$8 -> 0.17438363
A18: CUST008 | B18: Robert Anderson | C18: South | D18: Books | E18: 877.58 | F18: 10 | G18: 0.15 | H18: 45411 | I18: 298.38 | J18: =SUMIFS($E$2:$E$201,$A$2:$A$201,A18) -> 9760.8 | K18: =IF(INDEX('Pivot Table'!$N$5:$N$34,MATCH(A18,'Pivot Table'!$I$5:$I$34,0))<=10,"Top 10","") -> Top 10 | L18: =ROUND(E18/(1-G18),2) -> 1032.45 | M18: =ROUND(L18*(1-$U$3),2) -> 929.21 | N18: =ROUND(M18-(E18-I18),2) -> 350.01 | O18: =I18/E18 -> 0.34000319 | P18: =DATE(YEAR(H18),MONTH(H18),1) -> 45383 | Q18: =IF(J18>='Pivot Table'!$R$4,"High Value","Standard") -> High Value | R18: =NOW() -> 46304.64 | T18: 0.1 | U18: =SUM($L$2:$L$201)*(1-T18) -> 196224.53 | V18: =U18-$U$7 -> 69293.784 | W18: =V18/U18 -> 0.35313517 | X18: =V18-$U$8 -> 1006.774 | Y18: =X18/$U$8 -> 0.014743273
A19: CUST001 | B19: Lisa Thomas | C19: West | D19: Books | E19: 636.7 | F19: 4 | G19: 0.2 | H19: 45411 | I19: 203.74 | J19: =SUMIFS($E$2:$E$201,$A$2:$A$201,A19) -> 6549.55 | K19: =IF(INDEX('Pivot Table'!$N$5:$N$34,MATCH(A19,'Pivot Table'!$I$5:$I$34,0))<=10,"Top 10","") | L19: =ROUND(E19/(1-G19),2) -> 795.88 | M19: =ROUND(L19*(1-$U$3),2) -> 716.29 | N19: =ROUND(M19-(E19-I19),2) -> 283.33 | O19: =I19/E19 -> 0.31999372 | P19: =DATE(YEAR(H19),MONTH(H19),1) -> 45383 | Q19: =IF(J19>='Pivot Table'!$R$4,"High Value","Standard") -> Standard | R19: =NOW() -> 46304.64 | T19: 0.15 | U19: =SUM($L$2:$L$201)*(1-T19) -> 185323.17 | V19: =U19-$U$7 -> 58392.421 | W19: =V19/U19 -> 0.3150843 | X19: =V19-$U$8 -> -9894.589 | Y19: =X19/$U$8 -> -0.14489709
A20: CUST006 | B20: Mary Jackson | C20: West | D20: Books | E20: 1506.14 | F20: 13 | G20: 0.2 | H20: 45412 | I20: 481.96 | J20: =SUMIFS($E$2:$E$201,$A$2:$A$201,A20) -> 2699.75 | K20: =IF(INDEX('Pivot Table'!$N$5:$N$34,MATCH(A20,'Pivot Table'!$I$5:$I$34,0))<=10,"Top 10","") | L20: =ROUND(E20/(1-G20),2) -> 1882.68 | M20: =ROUND(L20*(1-$U$3),2) -> 1694.41 | N20: =ROUND(M20-(E20-I20),2) -> 670.23 | O20: =I20/E20 -> 0.31999681 | P20: =DATE(YEAR(H20),MONTH(H20),1) -> 45383 | Q20: =IF(J20>='Pivot Table'!$R$4,"High Value","Standard") -> Standard | R20: =NOW() -> 46304.64 | T20: 0.2 | U20: =SUM($L$2:$L$201)*(1-T20) -> 174421.81 | V20: =U20-$U$7 -> 47491.058 | W20: =V20/U20 -> 0.27227707 | X20: =V20-$U$8 -> -20795.952 | Y20: =X20/$U$8 -> -0.30453745
A21: CUST026 | B21: Mary Davis | C21: Central | D21: Electronics | E21: 645.02 | F21: 4 | G21: 0 | H21: 45414 | I21: 161.26 | J21: =SUMIFS($E$2:$E$201,$A$2:$A$201,A21) -> 9371.81 | K21: =IF(INDEX('Pivot Table'!$N$5:$N$34,MATCH(A21,'Pivot Table'!$I$5:$I$34,0))<=10,"Top 10","") -> Top 10 | L21: =ROUND(E21/(1-G21),2) -> 645.02 | M21: =ROUND(L21*(1-$U$3),2) -> 580.52 | N21: =ROUND(M21-(E21-I21),2) -> 96.76 | O21: =I21/E21 -> 0.25000775 | P21: =DATE(YEAR(H21),MONTH(H21),1) -> 45413 | Q21: =IF(J21>='Pivot Table'!$R$4,"High Value","Standard") -> High Value | R21: =NOW() -> 46304.64 | T21: 0.25 | U21: =SUM($L$2:$L$201)*(1-T21) -> 163520.45 | V21: =U21-$U$7 -> 36589.695 | W21: =V21/U21 -> 0.2237622 | X21: =V21-$U$8 -> -31697.315 | Y21: =X21/$U$8 -> -0.46417781
A22: CUST007 | B22: Lisa Davis | C22: South | D22: Clothing | E22: 953.3 | F22: 11 | G22: 0 | H22: 45415 | I22: 476.65 | J22: =SUMIFS($E$2:$E$201,$A$2:$A$201,A22) -> 9941.88 | K22: =IF(INDEX('Pivot Table'!$N$5:$N$34,MATCH(A22,'Pivot Table'!$I$5:$I$34,0))<=10,"Top 10","") -> Top 10 | L22: =ROUND(E22/(1-G22),2) -> 953.3 | M22: =ROUND(L22*(1-$U$3),2) -> 857.97 | N22: =ROUND(M22-(E22-I22),2) -> 381.32 | O22: =I22/E22 -> 0.5 | P22: =DATE(YEAR(H22),MONTH(H22),1) -> 45413 | Q22: =IF(J22>='Pivot Table'!$R$4,"High Value","Standard") -> High Value | R22: =NOW() -> 46304.64 | T22: =U3 -> 0.1 | U22: =SUM($L$2:$L$201)*(1-T22) -> 196224.53 | V22: =U22-$U$7 -> 69293.784 | W22: =V22/U22 -> 0.35313517 | X22: =V22-$U$8 -> 1006.774 | Y22: =X22/$U$8 -> 0.014743273
A23: CUST022 | B23: Robert Anderson | C23: North | D23: Electronics | E23: 388.56 | F23: 14 | G23: 0.15 | H23: 45416 | I23: 82.57 | J23: =SUMIFS($E$2:$E$201,$A$2:$A$201,A23) -> 4418.28 | K23: =IF(INDEX('Pivot Table'!$N$5:$N$34,MATCH(A23,'Pivot Table'!$I$5:$I$34,0))<=10,"Top 10","") | L23: =ROUND(E23/(1-G23),2) -> 457.13 | M23: =ROUND(L23*(1-$U$3),2) -> 411.42 | N23: =ROUND(M23-(E23-I23),2) -> 105.43 | O23: =I23/E23 -> 0.21250257 | P23: =DATE(YEAR(H23),MONTH(H23),1) -> 45413 | Q23: =IF(J23>='Pivot Table'!$R$4,"High Value","Standard") -> Standard | R23: =NOW() -> 46304.64
A24: CUST019 | B24: Mary Davis | C24: West | D24: Books | E24: 743.17 | F24: 9 | G24: 0 | H24: 45416 | I24: 297.27 | J24: =SUMIFS($E$2:$E$201,$A$2:$A$201,A24) -> 4640.11 | K24: =IF(INDEX('Pivot Table'!$N$5:$N$34,MATCH(A24,'Pivot Table'!$I$5:$I$34,0))<=10,"Top 10","") | L24: =ROUND(E24/(1-G24),2) -> 743.17 | M24: =ROUND(L24*(1-$U$3),2) -> 668.85 | N24: =ROUND(M24-(E24-I24),2) -> 222.95 | O24: =I24/E24 -> 0.40000269 | P24: =DATE(YEAR(H24),MONTH(H24),1) -> 45413 | Q24: =IF(J24>='Pivot Table'!$R$4,"High Value","Standard") -> Standard | R24: =NOW() -> 46304.64
A25: CUST023 | B25: Mary Davis | C25: Central | D25: Electronics | E25: 706.37 | F25: 6 | G25: 0 | H25: 45416 | I25: 176.59 | J25: =SUMIFS($E$2:$E$201,$A$2:$A$201,A25) -> 5913.68 | K25: =IF(INDEX('Pivot Table'!$N$5:$N$34,MATCH(A25,'Pivot Table'!$I$5:$I$34,0))<=10,"Top 10","") | L25: =ROUND(E25/(1-G25),2) -> 706.37 | M25: =ROUND(L25*(1-$U$3),2) -> 635.73 | N25: =ROUND(M25-(E25-I25),2) -> 105.95 | O25: =I25/E25 -> 0.24999646 | P25: =DATE(YEAR(H25),MONTH(H25),1) -> 45413 | Q25: =IF(J25>='Pivot Table'!$R$4,"High Value","Standard") -> Standard | R25: =NOW() -> 46304.64
A26: CUST012 | B26: Mary Davis | C26: Central | D26: Office Supplies | E26: 925.31 | F26: 8 | G26: 0.1 | H26: 45418 | I26: 374.75 | J26: =SUMIFS($E$2:$E$201,$A$2:$A$201,A26) -> 8339 | K26: =IF(INDEX('Pivot Table'!$N$5:$N$34,MATCH(A26,'Pivot Table'!$I$5:$I$34,0))<=10,"Top 10","") -> Top 10 | L26: =ROUND(E26/(1-G26),2) -> 1028.12 | M26: =ROUND(L26*(1-$U$3),2) -> 925.31 | N26: =ROUND(M26-(E26-I26),2) -> 374.75 | O26: =I26/E26 -> 0.40499941 | P26: =DATE(YEAR(H26),MONTH(H26),1) -> 45413 | Q26: =IF(J26>='Pivot Table'!$R$4,"High Value","Standard") -> High Value | R26: =NOW() -> 46304.64
A27: CUST010 | B27: Linda Brown | C27: South | D27: Electronics | E27: 1173.12 | F27: 18 | G27: 0 | H27: 45418 | I27: 293.28 | J27: =SUMIFS($E$2:$E$201,$A$2:$A$201,A27) -> 4259.22 | K27: =IF(INDEX('Pivot Table'!$N$5:$N$34,MATCH(A27,'Pivot Table'!$I$5:$I$34,0))<=10,"Top 10","") | L27: =ROUND(E27/(1-G27),2) -> 1173.12 | M27: =ROUND(L27*(1-$U$3),2) -> 1055.81 | N27: =ROUND(M27-(E27-I27),2) -> 175.97 | O27: =I27/E27 -> 0.25 | P27: =DATE(YEAR(H27),MONTH(H27),1) -> 45413 | Q27: =IF(J27>='Pivot Table'!$R$4,"High Value","Standard") -> Standard | R27: =NOW() -> 46304.64
A28: CUST030 | B28: John Brown | C28: North | D28: Furniture | E28: 675.54 | F28: 17 | G28: 0 | H28: 45420 | I28: 236.44 | J28: =SUMIFS($E$2:$E$201,$A$2:$A$201,A28) -> 7928.71 | K28: =IF(INDEX('Pivot Table'!$N$5:$N$34,MATCH(A28,'Pivot Table'!$I$5:$I$34,0))<=10,"Top 10","") -> Top 10 | L28: =ROUND(E28/(1-G28),2) -> 675.54 | M28: =ROUND(L28*(1-$U$3),2) -> 607.99 | N28: =ROUND(M28-(E28-I28),2) -> 168.89 | O28: =I28/E28 -> 0.35000148 | P28: =DATE(YEAR(H28),MONTH(H28),1) -> 45413 | Q28: =IF(J28>='Pivot Table'!$R$4,"High Value","Standard") -> Standard | R28: =NOW() -> 46304.64
A29: CUST007 | B29: Robert Anderson | C29: Central | D29: Books | E29: 939.09 | F29: 2 | G29: 0.05 | H29: 45422 | I29: 356.85 | J29: =SUMIFS($E$2:$E$201,$A$2:$A$201,A29) -> 9941.88 | K29: =IF(INDEX('Pivot Table'!$N$5:$N$34,MATCH(A29,'Pivot Table'!$I$5:$I$34,0))<=10,"Top 10","") -> Top 10 | L29: =ROUND(E29/(1-G29),2) -> 988.52 | M29: =ROUND(L29*(1-$U$3),2) -> 889.67 | N29: =ROUND(M29-(E29-I29),2) -> 307.43 | O29: =I29/E29 -> 0.37999553 | P29: =DATE(YEAR(H29),MONTH(H29),1) -> 45413 | Q29: =IF(J29>='Pivot Table'!$R$4,"High Value","Standard") -> High Value | R29: =NOW() -> 46304.64
A30: CUST028 | B30: Linda Taylor | C30: East | D30: Office Supplies | E30: 983.34 | F30: 19 | G30: 0.1 | H30: 45426 | I30: 398.25 | J30: =SUMIFS($E$2:$E$201,$A$2:$A$201,A30) -> 10293.87 | K30: =IF(INDEX('Pivot Table'!$N$5:$N$34,MATCH(A30,'Pivot Table'!$I$5:$I$34,0))<=10,"Top 10","") -> Top 10 | L30: =ROUND(E30/(1-G30),2) -> 1092.6 | M30: =ROUND(L30*(1-$U$3),2) -> 983.34 | N30: =ROUND(M30-(E30-I30),2) -> 398.25 | O30: =I30/E30 -> 0.40499725 | P30: =DATE(YEAR(H30),MONTH(H30),1) -> 45413 | Q30: =IF(J30>='Pivot Table'!$R$4,"High Value","Standard") -> High Value | R30: =NOW() -> 46304.64
A31: CUST028 | B31: James Wilson | C31: South | D31: Electronics | E31: 801.21 | F31: 3 | G31: 0.2 | H31: 45426 | I31: 160.24 | J31: =SUMIFS($E$2:$E$201,$A$2:$A$201,A31) -> 10293.87 | K31: =IF(INDEX('Pivot Table'!$N$5:$N$34,MATCH(A31,'Pivot Table'!$I$5:$I$34,0))<=10,"Top 10","") -> Top 10 | L31: =ROUND(E31/(1-G31),2) -> 1001.51 | M31: =ROUND(L31*(1-$U$3),2) -> 901.36 | N31: =ROUND(M31-(E31-I31),2) -> 260.39 | O31: =I31/E31 -> 0.1999975 | P31: =DATE(YEAR(H31),MONTH(H31),1) -> 45413 | Q31: =IF(J31>='Pivot Table'!$R$4,"High Value","Standard") -> High Value | R31: =NOW() -> 46304.64
A32: CUST025 | B32: David Brown | C32: North | D32: Electronics | E32: 1450.71 | F32: 5 | G32: 0.1 | H32: 45427 | I32: 326.41 | J32: =SUMIFS($E$2:$E$201,$A$2:$A$201,A32) -> 6716.52 | K32: =IF(INDEX('Pivot Table'!$N$5:$N$34,MATCH(A32,'Pivot Table'!$I$5:$I$34,0))<=10,"Top 10","") | L32: =ROUND(E32/(1-G32),2) -> 1611.9 | M32: =ROUND(L32*(1-$U$3),2) -> 1450.71 | N32: =ROUND(M32-(E32-I32),2) -> 326.41 | O32: =I32/E32 -> 0.22500017 | P32: =DATE(YEAR(H32),MONTH(H32),1) -> 45413 | Q32: =IF(J32>='Pivot Table'!$R$4,"High Value","Standard") -> Standard | R32: =NOW() -> 46304.64
A33: CUST022 | B33: David Davis | C33: Central | D33: Books | E33: 1023.21 | F33: 18 | G33: 0.05 | H33: 45428 | I33: 388.82 | J33: =SUMIFS($E$2:$E$201,$A$2:$A$201,A33) -> 4418.28 | K33: =IF(INDEX('Pivot Table'!$N$5:$N$34,MATCH(A33,'Pivot Table'!$I$5:$I$34,0))<=10,"Top 10","") | L33: =ROUND(E33/(1-G33),2) -> 1077.06 | M33: =ROUND(L33*(1-$U$3),2) -> 969.35 | N33: =ROUND(M33-(E33-I33),2) -> 334.96 | O33: =I33/E33 -> 0.3800002 | P33: =DATE(YEAR(H33),MONTH(H33),1) -> 45413 | Q33: =IF(J33>='Pivot Table'!$R$4,"High Value","Standard") -> Standard | R33: =NOW() -> 46304.64
A34: CUST001 | B34: Mary Jackson | C34: West | D34: Furniture | E34: 853.72 | F34: 5 | G34: 0.15 | H34: 45428 | I34: 253.98 | J34: =SUMIFS($E$2:$E$201,$A$2:$A$201,A34) -> 6549.55 | K34: =IF(INDEX('Pivot Table'!$N$5:$N$34,MATCH(A34,'Pivot Table'!$I$5:$I$34,0))<=10,"Top 10","") | L34: =ROUND(E34/(1-G34),2) -> 1004.38 | M34: =ROUND(L34*(1-$U$3),2) -> 903.94 | N34: =ROUND(M34-(E34-I34),2) -> 304.2 | O34: =I34/E34 -> 0.29749801 | P34: =DATE(YEAR(H34),MONTH(H34),1) -> 45413 | Q34: =IF(J34>='Pivot Table'!$R$4,"High Value","Standard") -> Standard | R34: =NOW() -> 46304.64
... A41: CUST016 | B41: Emma Wilson | C41: East | D41: Books | E41: 580.43 | F41: 19 | G41: 0.15 | H41: 45435 | I41: 197.35 | J41: =SUMIFS($E$2:$E$201,$A$2:$A$201,A41) -> 3369.17 | K41: =IF(INDEX('Pivot Table'!$N$5:$N$34,MATCH(A41,'Pivot Table'!$I$5:$I$34,0))<=10,"Top 10","") | L41: =ROUND(E41/(1-G41),2) -> 682.86 | M41: =ROUND(L41*(1-$U$3),2) -> 614.57 | N41: =ROUND(M41-(E41-I41),2) -> 231.49 | O41: =I41/E41 -> 0.34000655 | P41: =DATE(YEAR(H41),MONTH(H41),1) -> 45413 | Q41: =IF(J41>='Pivot Table'!$R$4,"High Value","Standard") -> Standard | R41: =NOW() -> 46304.64
A42: CUST005 | B42: David Smith | C42: South | D42: Books | E42: 1151.21 | F42: 15 | G42: 0.1 | H42: 45445 | I42: 414.44 | J42: =SUMIFS($E$2:$E$201,$A$2:$A$201,A42) -> 6666.13 | K42: =IF(INDEX('Pivot Table'!$N$5:$N$34,MATCH(A42,'Pivot Table'!$I$5:$I$34,0))<=10,"Top 10","") | L42: =ROUND(E42/(1-G42),2) -> 1279.12 | M42: =ROUND(L42*(1-$U$3),2) -> 1151.21 | N42: =ROUND(M42-(E42-I42),2) -> 414.44 | O42: =I42/E42 -> 0.36000382 | P42: =DATE(YEAR(H42),MONTH(H42),1) -> 45444 | Q42: =IF(J42>='Pivot Table'!$R$4,"High Value","Standard") -> Standard | R42: =NOW() -> 46304.64 | T42: DESCRIPTIVE STATISTICS – ToolPak-format table for Sales, Quantity, Discount, Profit (values computed to match Excel)
A43: CUST028 | B43: James Wilson | C43: Central | D43: Office Supplies | E43: 1025.98 | F43: 5 | G43: 0.2 | H43: 45447 | I43: 369.35 | J43: =SUMIFS($E$2:$E$201,$A$2:$A$201,A43) -> 10293.87 | K43: =IF(INDEX('Pivot Table'!$N$5:$N$34,MATCH(A43,'Pivot Table'!$I$5:$I$34,0))<=10,"Top 10","") -> Top 10 | L43: =ROUND(E43/(1-G43),2) -> 1282.48 | M43: =ROUND(L43*(1-$U$3),2) -> 1154.23 | N43: =ROUND(M43-(E43-I43),2) -> 497.6 | O43: =I43/E43 -> 0.35999727 | P43: =DATE(YEAR(H43),MONTH(H43),1) -> 45444 | Q43: =IF(J43>='Pivot Table'!$R$4,"High Value","Standard") -> High Value | R43: =NOW() -> 46304.64 | T43: Sales | V43: Quantity | X43: Discount | Z43: Profit
A44: CUST023 | B44: David Davis | C44: East | D44: Office Supplies | E44: 556.42 | F44: 11 | G44: 0.15 | H44: 45447 | I44: 212.83 | J44: =SUMIFS($E$2:$E$201,$A$2:$A$201,A44) -> 5913.68 | K44: =IF(INDEX('Pivot Table'!$N$5:$N$34,MATCH(A44,'Pivot Table'!$I$5:$I$34,0))<=10,"Top 10","") | L44: =ROUND(E44/(1-G44),2) -> 654.61 | M44: =ROUND(L44*(1-$U$3),2) -> 589.15 | N44: =ROUND(M44-(E44-I44),2) -> 245.56 | O44: =I44/E44 -> 0.38249883 | P44: =DATE(YEAR(H44),MONTH(H44),1) -> 45444 | Q44: =IF(J44>='Pivot Table'!$R$4,"High Value","Standard") -> Standard | R44: =NOW() -> 46304.64 | T44: Mean | U44: 976.0888 | V44: Mean | W44: 9.995 | X44: Mean | Y44: 0.09725 | Z44: Mean | AA44: 341.43505
A45: CUST021 | B45: James Wilson | C45: Central | D45: Books | E45: 840.85 | F45: 19 | G45: 0.1 | H45: 45448 | I45: 302.71 | J45: =SUMIFS($E$2:$E$201,$A$2:$A$201,A45) -> 8740.18 | K45: =IF(INDEX('Pivot Table'!$N$5:$N$34,MATCH(A45,'Pivot Table'!$I$5:$I$34,0))<=10,"Top 10","") -> Top 10 | L45: =ROUND(E45/(1-G45),2) -> 934.28 | M45: =ROUND(L45*(1-$U$3),2) -> 840.85 | N45: =ROUND(M45-(E45-I45),2) -> 302.71 | O45: =I45/E45 -> 0.36000476 | P45: =DATE(YEAR(H45),MONTH(H45),1) -> 45444 | Q45: =IF(J45>='Pivot Table'!$R$4,"High Value","Standard") -> High Value | R45: =NOW() -> 46304.64 | T45: Standard Error | U45: 21.16185 | V45: Standard Error | W45: 0.39927683 | X45: Standard Error | Y45: 0.0051142414 | Z45: Standard Error | AA45: 9.6001196
A46: CUST026 | B46: Emma Wilson | C46: North | D46: Furniture | E46: 1227.25 | F46: 12 | G46: 0.15 | H46: 45448 | I46: 365.11 | J46: =SUMIFS($E$2:$E$201,$A$2:$A$201,A46) -> 9371.81 | K46: =IF(INDEX('Pivot Table'!$N$5:$N$34,MATCH(A46,'Pivot Table'!$I$5:$I$34,0))<=10,"Top 10","") -> Top 10 | L46: =ROUND(E46/(1-G46),2) -> 1443.82 | M46: =ROUND(L46*(1-$U$3),2) -> 1299.44 | N46: =ROUND(M46-(E46-I46),2) -> 437.3 | O46: =I46/E46 -> 0.29750255 | P46: =DATE(YEAR(H46),MONTH(H46),1) -> 45444 | Q46: =IF(J46>='Pivot Table'!$R$4,"High Value","Standard") -> High Value | R46: =NOW() -> 46304.64 | T46: Median | U46: 976.72 | V46: Median | W46: 10 | X46: Median | Y46: 0.1 | Z46: Median | AA46: 332.255
A47: CUST017 | B47: Linda Davis | C47: Central | D47: Electronics | E47: 856.7 | F47: 2 | G47: 0 | H47: 45449 | I47: 214.18 | J47: =SUMIFS($E$2:$E$201,$A$2:$A$201,A47) -> 3419.2 | K47: =IF(INDEX('Pivot Table'!$N$5:$N$34,MATCH(A47,'Pivot Table'!$I$5:$I$34,0))<=10,"Top 10","") | L47: =ROUND(E47/(1-G47),2) -> 856.7 | M47: =ROUND(L47*(1-$U$3),2) -> 771.03 | N47: =ROUND(M47-(E47-I47),2) -> 128.51 | O47: =I47/E47 -> 0.25000584 | P47: =DATE(YEAR(H47),MONTH(H47),1) -> 45444 | Q47: =IF(J47>='Pivot Table'!$R$4,"High Value","Standard") -> Standard | R47: =NOW() -> 46304.64 | T47: Mode | U47: #N/A | V47: Mode | W47: 8 | X47: Mode | Y47: 0.2 | Z47: Mode | AA47: #N/A
A48: CUST025 | B48: David Davis | C48: Central | D48: Office Supplies | E48: 1225.42 | F48: 8 | G48: 0.15 | H48: 45449 | I48: 468.72 | J48: =SUMIFS($E$2:$E$201,$A$2:$A$201,A48) -> 6716.52 | K48: =IF(INDEX('Pivot Table'!$N$5:$N$34,MATCH(A48,'Pivot Table'!$I$5:$I$34,0))<=10,"Top 10","") | L48: =ROUND(E48/(1-G48),2) -> 1441.67 | M48: =ROUND(L48*(1-$U$3),2) -> 1297.5 | N48: =ROUND(M48-(E48-I48),2) -> 540.8 | O48: =I48/E48 -> 0.38249743 | P48: =DATE(YEAR(H48),MONTH(H48),1) -> 45444 | Q48: =IF(J48>='Pivot Table'!$R$4,"High Value","Standard") -> Standard | R48: =NOW() -> 46304.64 | T48: Standard Deviation | U48: 299.27376 | V48: Standard Deviation | W48: 5.646627 | X48: Standard Deviation | Y48: 0.072326295 | Z48: Standard Deviation | AA48: 135.76619
A49: CUST011 | B49: Mary Davis | C49: North | D49: Office Supplies | E49: 1001.57 | F49: 12 | G49: 0 | H49: 45450 | I49: 450.71 | J49: =SUMIFS($E$2:$E$201,$A$2:$A$201,A49) -> 3762.29 | K49: =IF(INDEX('Pivot Table'!$N$5:$N$34,MATCH(A49,'Pivot Table'!$I$5:$I$34,0))<=10,"Top 10","") | L49: =ROUND(E49/(1-G49),2) -> 1001.57 | M49: =ROUND(L49*(1-$U$3),2) -> 901.41 | N49: =ROUND(M49-(E49-I49),2) -> 350.55 | O49: =I49/E49 -> 0.45000349 | P49: =DATE(YEAR(H49),MONTH(H49),1) -> 45444 | Q49: =IF(J49>='Pivot Table'!$R$4,"High Value","Standard") -> Standard | R49: =NOW() -> 46304.64 | T49: Sample Variance | U49: 89564.783 | V49: Sample Variance | W49: 31.884397 | X49: Sample Variance | Y49: 0.005231093 | Z49: Sample Variance | AA49: 18432.459
A50: CUST021 | B50: Michael Anderson | C50: East | D50: Furniture | E50: 1186.85 | F50: 19 | G50: 0.2 | H50: 45451 | I50: 332.32 | J50: =SUMIFS($E$2:$E$201,$A$2:$A$201,A50) -> 8740.18 | K50: =IF(INDEX('Pivot Table'!$N$5:$N$34,MATCH(A50,'Pivot Table'!$I$5:$I$34,0))<=10,"Top 10","") -> Top 10 | L50: =ROUND(E50/(1-G50),2) -> 1483.56 | M50: =ROUND(L50*(1-$U$3),2) -> 1335.2 | N50: =ROUND(M50-(E50-I50),2) -> 480.67 | O50: =I50/E50 -> 0.28000169 | P50: =DATE(YEAR(H50),MONTH(H50),1) -> 45444 | Q50: =IF(J50>='Pivot Table'!$R$4,"High Value","Standard") -> High Value | R50: =NOW() -> 46304.64 | T50: Kurtosis | U50: -0.088595232 | V50: Kurtosis | W50: -1.2091054 | X50: Kurtosis | Y50: -1.3257012 | Z50: Kurtosis | AA50: 0.26450644
A51: CUST008 | B51: John Brown | C51: South | D51: Electronics | E51: 775.45 | F51: 6 | G51: 0.1 | H51: 45457 | I51: 174.48 | J51: =SUMIFS($E$2:$E$201,$A$2:$A$201,A51) -> 9760.8 | K51: =IF(INDEX('Pivot Table'!$N$5:$N$34,MATCH(A51,'Pivot Table'!$I$5:$I$34,0))<=10,"Top 10","") -> Top 10 | L51: =ROUND(E51/(1-G51),2) -> 861.61 | M51: =ROUND(L51*(1-$U$3),2) -> 775.45 | N51: =ROUND(M51-(E51-I51),2) -> 174.48 | O51: =I51/E51 -> 0.22500484 | P51: =DATE(YEAR(H51),MONTH(H51),1) -> 45444 | Q51: =IF(J51>='Pivot Table'!$R$4,"High Value","Standard") -> High Value | R51: =NOW() -> 46304.64 | T51: Skewness | U51: 0.14685797 | V51: Skewness | W51: 0.060845864 | X51: Skewness | Y51: 0.096827386 | Z51: Skewness | AA51: 0.57339636
A52: CUST007 | B52: Linda Jackson | C52: South | D52: Electronics | E52: 1021.47 | F52: 6 | G52: 0.05 | H52: 45461 | I52: 242.6 | J52: =SUMIFS($E$2:$E$201,$A$2:$A$201,A52) -> 9941.88 | K52: =IF(INDEX('Pivot Table'!$N$5:$N$34,MATCH(A52,'Pivot Table'!$I$5:$I$34,0))<=10,"Top 10","") -> Top 10 | L52: =ROUND(E52/(1-G52),2) -> 1075.23 | M52: =ROUND(L52*(1-$U$3),2) -> 967.71 | N52: =ROUND(M52-(E52-I52),2) -> 188.84 | O52: =I52/E52 -> 0.23750086 | P52: =DATE(YEAR(H52),MONTH(H52),1) -> 45444 | Q52: =IF(J52>='Pivot Table'!$R$4,"High Value","Standard") -> High Value | R52: =NOW() -> 46304.64 | T52: Range | U52: 1665.15 | V52: Range | W52: 18 | X52: Range | Y52: 0.2 | Z52: Range | AA52: 704.83
A53: CUST015 | B53: James Wilson | C53: South | D53: Clothing | E53: 1226.62 | F53: 7 | G53: 0.1 | H53: 45463 | I53: 551.98 | J53: =SUMIFS($E$2:$E$201,$A$2:$A$201,A53) -> 11611.06 | K53: =IF(INDEX('Pivot Table'!$N$5:$N$34,MATCH(A53,'Pivot Table'!$I$5:$I$34,0))<=10,"Top 10","") -> Top 10 | L53: =ROUND(E53/(1-G53),2) -> 1362.91 | M53: =ROUND(L53*(1-$U$3),2) -> 1226.62 | N53: =ROUND(M53-(E53-I53),2) -> 551.98 | O53: =I53/E53 -> 0.45000082 | P53: =DATE(YEAR(H53),MONTH(H53),1) -> 45444 | Q53: =IF(J53>='Pivot Table'!$R$4,"High Value","Standard") -> High Value | R53: =NOW() -> 46304.64 | T53: Minimum | U53: 258.51 | V53: Minimum | W53: 1 | X53: Minimum | Y53: 0 | Z53: Minimum | AA53: 64.63
A54: CUST030 | B54: Sarah Davis | C54: South | D54: Furniture | E54: 1086.93 | F54: 2 | G54: 0 | H54: 45464 | I54: 380.43 | J54: =SUMIFS($E$2:$E$201,$A$2:$A$201,A54) -> 7928.71 | K54: =IF(INDEX('Pivot Table'!$N$5:$N$34,MATCH(A54,'Pivot Table'!$I$5:$I$34,0))<=10,"Top 10","") -> Top 10 | L54: =ROUND(E54/(1-G54),2) -> 1086.93 | M54: =ROUND(L54*(1-$U$3),2) -> 978.24 | N54: =ROUND(M54-(E54-I54),2) -> 271.74 | O54: =I54/E54 -> 0.35000414 | P54: =DATE(YEAR(H54),MONTH(H54),1) -> 45444 | Q54: =IF(J54>='Pivot Table'!$R$4,"High Value","Standard") -> Standard | R54: =NOW() -> 46304.64 | T54: Maximum | U54: 1923.66 | V54: Maximum | W54: 19 | X54: Maximum | Y54: 0.2 | Z54: Maximum | AA54: 769.46
A55: CUST002 | B55: Lisa Davis | C55: West | D55: Books | E55: 942.9 | F55: 18 | G55: 0.1 | H55: 45466 | I55: 339.44 | J55: =SUMIFS($E$2:$E$201,$A$2:$A$201,A55) -> 6481.43 | K55: =IF(INDEX('Pivot Table'!$N$5:$N$34,MATCH(A55,'Pivot Table'!$I$5:$I$34,0))<=10,"Top 10","") | L55: =ROUND(E55/(1-G55),2) -> 1047.67 | M55: =ROUND(L55*(1-$U$3),2) -> 942.9 | N55: =ROUND(M55-(E55-I55),2) -> 339.44 | O55: =I55/E55 -> 0.35999576 | P55: =DATE(YEAR(H55),MONTH(H55),1) -> 45444 | Q55: =IF(J55>='Pivot Table'!$R$4,"High Value","Standard") -> Standard | R55: =NOW() -> 46304.64 | T55: Sum | U55: 195217.76 | V55: Sum | W55: 1999 | X55: Sum | Y55: 19.45 | Z55: Sum | AA55: 68287.01
A56: CUST009 | B56: Emma Davis | C56: North | D56: Electronics | E56: 818.8 | F56: 15 | G56: 0.15 | H56: 45468 | I56: 173.99 | J56: =SUMIFS($E$2:$E$201,$A$2:$A$201,A56) -> 6505.2 | K56: =IF(INDEX('Pivot Table'!$N$5:$N$34,MATCH(A56,'Pivot Table'!$I$5:$I$34,0))<=10,"Top 10","") | L56: =ROUND(E56/(1-G56),2) -> 963.29 | M56: =ROUND(L56*(1-$U$3),2) -> 866.96 | N56: =ROUND(M56-(E56-I56),2) -> 222.15 | O56: =I56/E56 -> 0.21249389 | P56: =DATE(YEAR(H56),MONTH(H56),1) -> 45444 | Q56: =IF(J56>='Pivot Table'!$R$4,"High Value","Standard") -> Standard | R56: =NOW() -> 46304.64 | T56: Count | U56: 200 | V56: Count | W56: 200 | X56: Count | Y56: 200 | Z56: Count | AA56: 200
A57: CUST005 | B57: Robert Anderson | C57: South | D57: Furniture | E57: 919.04 | F57: 10 | G57: 0.2 | H57: 45468 | I57: 257.33 | J57: =SUMIFS($E$2:$E$201,$A$2:$A$201,A57) -> 6666.13 | K57: =IF(INDEX('Pivot Table'!$N$5:$N$34,MATCH(A57,'Pivot Table'!$I$5:$I$34,0))<=10,"Top 10","") | L57: =ROUND(E57/(1-G57),2) -> 1148.8 | M57: =ROUND(L57*(1-$U$3),2) -> 1033.92 | N57: =ROUND(M57-(E57-I57),2) -> 372.21 | O57: =I57/E57 -> 0.27999869 | P57: =DATE(YEAR(H57),MONTH(H57),1) -> 45444 | Q57: =IF(J57>='Pivot Table'!$R$4,"High Value","Standard") -> Standard | R57: =NOW() -> 46304.64 | T57: Confidence Level(95.0%) | U57: 41.730249 | V57: Confidence Level(95.0%) | W57: 0.78735655 | X57: Confidence Level(95.0%) | Y57: 0.010085062 | Z57: Confidence Level(95.0%) | AA57: 18.931019
A58: CUST030 | B58: Emma Taylor | C58: Central | D58: Books | E58: 973.26 | F58: 11 | G58: 0 | H58: 45470 | I58: 389.3 | J58: =SUMIFS($E$2:$E$201,$A$2:$A$201,A58) -> 7928.71 | K58: =IF(INDEX('Pivot Table'!$N$5:$N$34,MATCH(A58,'Pivot Table'!$I$5:$I$34,0))<=10,"Top 10","") -> Top 10 | L58: =ROUND(E58/(1-G58),2) -> 973.26 | M58: =ROUND(L58*(1-$U$3),2) -> 875.93 | N58: =ROUND(M58-(E58-I58),2) -> 291.97 | O58: =I58/E58 -> 0.39999589 | P58: =DATE(YEAR(H58),MONTH(H58),1) -> 45444 | Q58: =IF(J58>='Pivot Table'!$R$4,"High Value","Standard") -> Standard | R58: =NOW() -> 46304.64
A59: CUST029 | B59: Sarah Davis | C59: North | D59: Electronics | E59: 741.61 | F59: 1 | G59: 0.2 | H59: 45471 | I59: 148.32 | J59: =SUMIFS($E$2:$E$201,$A$2:$A$201,A59) -> 5779.05 | K59: =IF(INDEX('Pivot Table'!$N$5:$N$34,MATCH(A59,'Pivot Table'!$I$5:$I$34,0))<=10,"Top 10","") | L59: =ROUND(E59/(1-G59),2) -> 927.01 | M59: =ROUND(L59*(1-$U$3),2) -> 834.31 | N59: =ROUND(M59-(E59-I59),2) -> 241.02 | O59: =I59/E59 -> 0.1999973 | P59: =DATE(YEAR(H59),MONTH(H59),1) -> 45444 | Q59: =IF(J59>='Pivot Table'!$R$4,"High Value","Standard") -> Standard | R59: =NOW() -> 46304.64
A60: CUST003 | B60: Emma Davis | C60: North | D60: Books | E60: 1248.82 | F60: 2 | G60: 0.1 | H60: 45473 | I60: 449.58 | J60: =SUMIFS($E$2:$E$201,$A$2:$A$201,A60) -> 8490.18 | K60: =IF(INDEX('Pivot Table'!$N$5:$N$34,MATCH(A60,'Pivot Table'!$I$5:$I$34,0))<=10,"Top 10","") -> Top 10 | L60: =ROUND(E60/(1-G60),2) -> 1387.58 | M60: =ROUND(L60*(1-$U$3),2) -> 1248.82 | N60: =ROUND(M60-(E60-I60),2) -> 449.58 | O60: =I60/E60 -> 0.36000384 | P60: =DATE(YEAR(H60),MONTH(H60),1) -> 45444 | Q60: =IF(J60>='Pivot Table'!$R$4,"High Value","Standard") -> High Value | R60: =NOW() -> 46304.64 | T60: REGRESSION – ToolPak-format output: Profit (Y) vs Sales (X) (values computed to match Excel) | AD60: RESIDUAL OUTPUT
A61: CUST012 | B61: Mary Wilson | C61: West | D61: Clothing | E61: 1360.36 | F61: 17 | G61: 0 | H61: 45473 | I61: 680.18 | J61: =SUMIFS($E$2:$E$201,$A$2:$A$201,A61) -> 8339 | K61: =IF(INDEX('Pivot Table'!$N$5:$N$34,MATCH(A61,'Pivot Table'!$I$5:$I$34,0))<=10,"Top 10","") -> Top 10 | L61: =ROUND(E61/(1-G61),2) -> 1360.36 | M61: =ROUND(L61*(1-$U$3),2) -> 1224.32 | N61: =ROUND(M61-(E61-I61),2) -> 544.14 | O61: =I61/E61 -> 0.5 | P61: =DATE(YEAR(H61),MONTH(H61),1) -> 45444 | Q61: =IF(J61>='Pivot Table'!$R$4,"High Value","Standard") -> High Value | R61: =NOW() -> 46304.64 | T61: SUMMARY OUTPUT
A62: CUST021 | B62: Mary Davis | C62: East | D62: Books | E62: 1383.3 | F62: 8 | G62: 0.1 | H62: 45478 | I62: 497.99 | J62: =SUMIFS($E$2:$E$201,$A$2:$A$201,A62) -> 8740.18 | K62: =IF(INDEX('Pivot Table'!$N$5:$N$34,MATCH(A62,'Pivot Table'!$I$5:$I$34,0))<=10,"Top 10","") -> Top 10 | L62: =ROUND(E62/(1-G62),2) -> 1537 | M62: =ROUND(L62*(1-$U$3),2) -> 1383.3 | N62: =ROUND(M62-(E62-I62),2) -> 497.99 | O62: =I62/E62 -> 0.36000145 | P62: =DATE(YEAR(H62),MONTH(H62),1) -> 45474 | Q62: =IF(J62>='Pivot Table'!$R$4,"High Value","Standard") -> High Value | R62: =NOW() -> 46304.64 | AD62: Observation | AE62: Predicted Profit | AF62: Residuals | AG62: Standard Residuals
A63: CUST010 | B63: David Brown | C63: Central | D63: Office Supplies | E63: 488.99 | F63: 9 | G63: 0 | H63: 45479 | I63: 220.05 | J63: =SUMIFS($E$2:$E$201,$A$2:$A$201,A63) -> 4259.22 | K63: =IF(INDEX('Pivot Table'!$N$5:$N$34,MATCH(A63,'Pivot Table'!$I$5:$I$34,0))<=10,"Top 10","") | L63: =ROUND(E63/(1-G63),2) -> 488.99 | M63: =ROUND(L63*(1-$U$3),2) -> 440.09 | N63: =ROUND(M63-(E63-I63),2) -> 171.15 | O63: =I63/E63 -> 0.4500092 | P63: =DATE(YEAR(H63),MONTH(H63),1) -> 45474 | Q63: =IF(J63>='Pivot Table'!$R$4,"High Value","Standard") -> Standard | R63: =NOW() -> 46304.64 | T63: Regression Statistics | AD63: 1 | AE63: 362.48683 | AF63: -30.93683 | AG63: -0.35946237
A64: CUST026 | B64: Mary Davis | C64: East | D64: Furniture | E64: 933.71 | F64: 17 | G64: 0.1 | H64: 45481 | I64: 294.12 | J64: =SUMIFS($E$2:$E$201,$A$2:$A$201,A64) -> 9371.81 | K64: =IF(INDEX('Pivot Table'!$N$5:$N$34,MATCH(A64,'Pivot Table'!$I$5:$I$34,0))<=10,"Top 10","") -> Top 10 | L64: =ROUND(E64/(1-G64),2) -> 1037.46 | M64: =ROUND(L64*(1-$U$3),2) -> 933.71 | N64: =ROUND(M64-(E64-I64),2) -> 294.12 | O64: =I64/E64 -> 0.31500145 | P64: =DATE(YEAR(H64),MONTH(H64),1) -> 45474 | Q64: =IF(J64>='Pivot Table'!$R$4,"High Value","Standard") -> High Value | R64: =NOW() -> 46304.64 | T64: Multiple R | U64: 0.77340306 | AD64: 2 | AE64: 385.35913 | AF64: 55.150868 | AG64: 0.64081101
A65: CUST003 | B65: James Davis | C65: West | D65: Electronics | E65: 1005.53 | F65: 17 | G65: 0.2 | H65: 45481 | I65: 201.11 | J65: =SUMIFS($E$2:$E$201,$A$2:$A$201,A65) -> 8490.18 | K65: =IF(INDEX('Pivot Table'!$N$5:$N$34,MATCH(A65,'Pivot Table'!$I$5:$I$34,0))<=10,"Top 10","") -> Top 10 | L65: =ROUND(E65/(1-G65),2) -> 1256.91 | M65: =ROUND(L65*(1-$U$3),2) -> 1131.22 | N65: =ROUND(M65-(E65-I65),2) -> 326.8 | O65: =I65/E65 -> 0.20000398 | P65: =DATE(YEAR(H65),MONTH(H65),1) -> 45474 | Q65: =IF(J65>='Pivot Table'!$R$4,"High Value","Standard") -> High Value | R65: =NOW() -> 46304.64 | T65: R Square | U65: 0.5981523 | AD65: 3 | AE65: 249.24806 | AF65: 36.09194 | AG65: 0.41936081
A66: CUST029 | B66: Emma Wilson | C66: South | D66: Electronics | E66: 1100.1 | F66: 5 | G66: 0.05 | H66: 45482 | I66: 261.27 | J66: =SUMIFS($E$2:$E$201,$A$2:$A$201,A66) -> 5779.05 | K66: =IF(INDEX('Pivot Table'!$N$5:$N$34,MATCH(A66,'Pivot Table'!$I$5:$I$34,0))<=10,"Top 10","") | L66: =ROUND(E66/(1-G66),2) -> 1158 | M66: =ROUND(L66*(1-$U$3),2) -> 1042.2 | N66: =ROUND(M66-(E66-I66),2) -> 203.37 | O66: =I66/E66 -> 0.23749659 | P66: =DATE(YEAR(H66),MONTH(H66),1) -> 45474 | Q66: =IF(J66>='Pivot Table'!$R$4,"High Value","Standard") -> Standard | R66: =NOW() -> 46304.64 | T66: Adjusted R Square | U66: 0.59612277 | AD66: 4 | AE66: 265.9453 | AF66: -104.2453 | AG66: -1.2112508
A67: CUST003 | B67: James Wilson | C67: North | D67: Furniture | E67: 1034.7 | F67: 15 | G67: 0.15 | H67: 45487 | I67: 307.82 | J67: =SUMIFS($E$2:$E$201,$A$2:$A$201,A67) -> 8490.18 | K67: =IF(INDEX('Pivot Table'!$N$5:$N$34,MATCH(A67,'Pivot Table'!$I$5:$I$34,0))<=10,"Top 10","") -> Top 10 | L67: =ROUND(E67/(1-G67),2) -> 1217.29 | M67: =ROUND(L67*(1-$U$3),2) -> 1095.56 | N67: =ROUND(M67-(E67-I67),2) -> 368.68 | O67: =I67/E67 -> 0.29749686 | P67: =DATE(YEAR(H67),MONTH(H67),1) -> 45474 | Q67: =IF(J67>='Pivot Table'!$R$4,"High Value","Standard") -> High Value | R67: =NOW() -> 46304.64 | T67: Standard Error | U67: 86.281231 | AD67: 5 | AE67: 296.14347 | AF67: -25.103472 | AG67: -0.29168319
A68: CUST002 | B68: Mary Davis | C68: South | D68: Books | E68: 876.44 | F68: 12 | G68: 0.05 | H68: 45488 | I68: 333.05 | J68: =SUMIFS($E$2:$E$201,$A$2:$A$201,A68) -> 6481.43 | K68: =IF(INDEX('Pivot Table'!$N$5:$N$34,MATCH(A68,'Pivot Table'!$I$5:$I$34,0))<=10,"Top 10","") | L68: =ROUND(E68/(1-G68),2) -> 922.57 | M68: =ROUND(L68*(1-$U$3),2) -> 830.31 | N68: =ROUND(M68-(E68-I68),2) -> 286.92 | O68: =I68/E68 -> 0.38000319 | P68: =DATE(YEAR(H68),MONTH(H68),1) -> 45474 | Q68: =IF(J68>='Pivot Table'!$R$4,"High Value","Standard") -> Standard | R68: =NOW() -> 46304.64 | T68: Observations | U68: 200 | AD68: 6 | AE68: 337.76903 | AF68: -33.589026 | AG68: -0.39027886
A69: CUST020 | B69: David Brown | C69: West | D69: Furniture | E69: 1371.34 | F69: 5 | G69: 0.05 | H69: 45488 | I69: 455.97 | J69: =SUMIFS($E$2:$E$201,$A$2:$A$201,A69) -> 4413.71 | K69: =IF(INDEX('Pivot Table'!$N$5:$N$34,MATCH(A69,'Pivot Table'!$I$5:$I$34,0))<=10,"Top 10","") | L69: =ROUND(E69/(1-G69),2) -> 1443.52 | M69: =ROUND(L69*(1-$U$3),2) -> 1299.17 | N69: =ROUND(M69-(E69-I69),2) -> 383.8 | O69: =I69/E69 -> 0.3324996 | P69: =DATE(YEAR(H69),MONTH(H69),1) -> 45474 | Q69: =IF(J69>='Pivot Table'!$R$4,"High Value","Standard") -> Standard | R69: =NOW() -> 46304.64 | T69: ANOVA | AD69: 7 | AE69: 461.23174 | AF69: -148.32174 | AG69: -1.7233855
A70: CUST021 | B70: Mary Jackson | C70: North | D70: Electronics | E70: 1020.26 | F70: 11 | G70: 0.05 | H70: 45494 | I70: 242.31 | J70: =SUMIFS($E$2:$E$201,$A$2:$A$201,A70) -> 8740.18 | K70: =IF(INDEX('Pivot Table'!$N$5:$N$34,MATCH(A70,'Pivot Table'!$I$5:$I$34,0))<=10,"Top 10","") -> Top 10 | L70: =ROUND(E70/(1-G70),2) -> 1073.96 | M70: =ROUND(L70*(1-$U$3),2) -> 966.56 | N70: =ROUND(M70-(E70-I70),2) -> 188.61 | O70: =I70/E70 -> 0.23749828 | P70: =DATE(YEAR(H70),MONTH(H70),1) -> 45474 | Q70: =IF(J70>='Pivot Table'!$R$4,"High Value","Standard") -> High Value | R70: =NOW() -> 46304.64 | U70: df | V70: SS | W70: MS | X70: F | Y70: Significance F | AD70: 8 | AE70: 375.95268 | AF70: -75.102683 | AG70: -0.87263588
A71: CUST008 | B71: James Davis | C71: Central | D71: Office Supplies | E71: 804.81 | F71: 1 | G71: 0.05 | H71: 45502 | I71: 344.06 | J71: =SUMIFS($E$2:$E$201,$A$2:$A$201,A71) -> 9760.8 | K71: =IF(INDEX('Pivot Table'!$N$5:$N$34,MATCH(A71,'Pivot Table'!$I$5:$I$34,0))<=10,"Top 10","") -> Top 10 | L71: =ROUND(E71/(1-G71),2) -> 847.17 | M71: =ROUND(L71*(1-$U$3),2) -> 762.45 | N71: =ROUND(M71-(E71-I71),2) -> 301.7 | O71: =I71/E71 -> 0.42750463 | P71: =DATE(YEAR(H71),MONTH(H71),1) -> 45474 | Q71: =IF(J71>='Pivot Table'!$R$4,"High Value","Standard") -> High Value | R71: =NOW() -> 46304.64 | T71: Regression | U71: 1 | V71: 2194058.2 | W71: 2194058.2 | X71: 294.72398 | Y71: 4.6269368e-41 | AD71: 9 | AE71: 174.93676 | AF71: 15.653238 | AG71: 0.18187869
A72: CUST030 | B72: David Brown | C72: Central | D72: Electronics | E72: 608.66 | F72: 1 | G72: 0.05 | H72: 45503 | I72: 144.56 | J72: =SUMIFS($E$2:$E$201,$A$2:$A$201,A72) -> 7928.71 | K72: =IF(INDEX('Pivot Table'!$N$5:$N$34,MATCH(A72,'Pivot Table'!$I$5:$I$34,0))<=10,"Top 10","") -> Top 10 | L72: =ROUND(E72/(1-G72),2) -> 640.69 | M72: =ROUND(L72*(1-$U$3),2) -> 576.62 | N72: =ROUND(M72-(E72-I72),2) -> 112.52 | O72: =I72/E72 -> 0.23750534 | P72: =DATE(YEAR(H72),MONTH(H72),1) -> 45474 | Q72: =IF(J72>='Pivot Table'!$R$4,"High Value","Standard") -> Standard | R72: =NOW() -> 46304.64 | T72: Residual | U72: 198 | V72: 1474001.2 | W72: 7444.4507 | AD72: 10 | AE72: 257.65808 | AF72: 92.561922 | AG72: 1.0754989
A73: CUST020 | B73: Linda Moore | C73: South | D73: Office Supplies | E73: 981.2 | F73: 19 | G73: 0 | H73: 45504 | I73: 441.54 | J73: =SUMIFS($E$2:$E$201,$A$2:$A$201,A73) -> 4413.71 | K73: =IF(INDEX('Pivot Table'!$N$5:$N$34,MATCH(A73,'Pivot Table'!$I$5:$I$34,0))<=10,"Top 10","") | L73: =ROUND(E73/(1-G73),2) -> 981.2 | M73: =ROUND(L73*(1-$U$3),2) -> 883.08 | N73: =ROUND(M73-(E73-I73),2) -> 343.42 | O73: =I73/E73 -> 0.45 | P73: =DATE(YEAR(H73),MONTH(H73),1) -> 45474 | Q73: =IF(J73>='Pivot Table'!$R$4,"High Value","Standard") -> Standard | R73: =NOW() -> 46304.64 | T73: Total | U73: 199 | V73: 3668059.4 | AD73: 11 | AE73: 550.80176 | AF73: 121.57824 | AG73: 1.4126463
A74: CUST024 | B74: David Brown | C74: East | D74: Electronics | E74: 539.77 | F74: 10 | G74: 0.15 | H74: 45509 | I74: 114.7 | J74: =SUMIFS($E$2:$E$201,$A$2:$A$201,A74) -> 7583.13 | K74: =IF(INDEX('Pivot Table'!$N$5:$N$34,MATCH(A74,'Pivot Table'!$I$5:$I$34,0))<=10,"Top 10","") | L74: =ROUND(E74/(1-G74),2) -> 635.02 | M74: =ROUND(L74*(1-$U$3),2) -> 571.52 | N74: =ROUND(M74-(E74-I74),2) -> 146.45 | O74: =I74/E74 -> 0.21249792 | P74: =DATE(YEAR(H74),MONTH(H74),1) -> 45505 | Q74: =IF(J74>='Pivot Table'!$R$4,"High Value","Standard") -> Standard | R74: =NOW() -> 46304.64 | AD74: 12 | AE74: 470.21365 | AF74: -13.553653 | AG74: -0.15748311
A75: CUST012 | B75: David Anderson | C75: South | D75: Books | E75: 804.45 | F75: 5 | G75: 0.2 | H75: 45509 | I75: 257.42 | J75: =SUMIFS($E$2:$E$201,$A$2:$A$201,A75) -> 8339 | K75: =IF(INDEX('Pivot Table'!$N$5:$N$34,MATCH(A75,'Pivot Table'!$I$5:$I$34,0))<=10,"Top 10","") -> Top 10 | L75: =ROUND(E75/(1-G75),2) -> 1005.56 | M75: =ROUND(L75*(1-$U$3),2) -> 905 | N75: =ROUND(M75-(E75-I75),2) -> 357.97 | O75: =I75/E75 -> 0.31999503 | P75: =DATE(YEAR(H75),MONTH(H75),1) -> 45505 | Q75: =IF(J75>='Pivot Table'!$R$4,"High Value","Standard") -> High Value | R75: =NOW() -> 46304.64 | U75: Coefficients | V75: Standard Error | W75: t Stat | X75: P-value | Y75: Lower 95% | Z75: Upper 95% | AA75: Lower 95.0% | AB75: Upper 95.0% | AD75: 13 | AE75: 417.04143 | AF75: 35.758572 | AG75: 0.41548733
A76: CUST024 | B76: Emma Davis | C76: West | D76: Electronics | E76: 1526.6 | F76: 13 | G76: 0.2 | H76: 45512 | I76: 305.32 | J76: =SUMIFS($E$2:$E$201,$A$2:$A$201,A76) -> 7583.13 | K76: =IF(INDEX('Pivot Table'!$N$5:$N$34,MATCH(A76,'Pivot Table'!$I$5:$I$34,0))<=10,"Top 10","") | L76: =ROUND(E76/(1-G76),2) -> 1908.25 | M76: =ROUND(L76*(1-$U$3),2) -> 1717.43 | N76: =ROUND(M76-(E76-I76),2) -> 496.15 | O76: =I76/E76 -> 0.2 | P76: =DATE(YEAR(H76),MONTH(H76),1) -> 45505 | Q76: =IF(J76>='Pivot Table'!$R$4,"High Value","Standard") -> Standard | R76: =NOW() -> 46304.64 | T76: Intercept | U76: -1.0315505 | V76: 20.860617 | W76: -0.049449663 | X76: 0.9606108 | Y76: -42.169052 | Z76: 40.105951 | AA76: -42.169052 | AB76: 40.105951 | AD76: 14 | AE76: 287.47031 | AF76: -14.060311 | AG76: -0.16337009
A77: CUST012 | B77: Linda Wilson | C77: West | D77: Electronics | E77: 1215.26 | F77: 5 | G77: 0.15 | H77: 45513 | I77: 258.24 | J77: =SUMIFS($E$2:$E$201,$A$2:$A$201,A77) -> 8339 | K77: =IF(INDEX('Pivot Table'!$N$5:$N$34,MATCH(A77,'Pivot Table'!$I$5:$I$34,0))<=10,"Top 10","") -> Top 10 | L77: =ROUND(E77/(1-G77),2) -> 1429.72 | M77: =ROUND(L77*(1-$U$3),2) -> 1286.75 | N77: =ROUND(M77-(E77-I77),2) -> 329.73 | O77: =I77/E77 -> 0.21249774 | P77: =DATE(YEAR(H77),MONTH(H77),1) -> 45505 | Q77: =IF(J77>='Pivot Table'!$R$4,"High Value","Standard") -> High Value | R77: =NOW() -> 46304.64 | T77: Sales | U77: 0.35085599 | V77: 0.020437189 | W77: 17.167527 | X77: 4.6269368e-41 | Y77: 0.3105535 | Z77: 0.39115848 | AA77: 0.3105535 | AB77: 0.39115848 | AD77: 15 | AE77: 181.99949 | AF77: -26.799493 | AG77: -0.31138966
A78: CUST005 | B78: Linda Taylor | C78: Central | D78: Furniture | E78: 1261.34 | F78: 3 | G78: 0 | H78: 45519 | I78: 441.47 | J78: =SUMIFS($E$2:$E$201,$A$2:$A$201,A78) -> 6666.13 | K78: =IF(INDEX('Pivot Table'!$N$5:$N$34,MATCH(A78,'Pivot Table'!$I$5:$I$34,0))<=10,"Top 10","") | L78: =ROUND(E78/(1-G78),2) -> 1261.34 | M78: =ROUND(L78*(1-$U$3),2) -> 1135.21 | N78: =ROUND(M78-(E78-I78),2) -> 315.34 | O78: =I78/E78 -> 0.35000079 | P78: =DATE(YEAR(H78),MONTH(H78),1) -> 45505 | Q78: =IF(J78>='Pivot Table'!$R$4,"High Value","Standard") -> Standard | R78: =NOW() -> 46304.64 | AD78: 16 | AE78: 526.28044 | AF78: -225.69044 | AG78: -2.6223507
A79: CUST004 | B79: Lisa Thomas | C79: North | D79: Furniture | E79: 518.07 | F79: 7 | G79: 0.05 | H79: 45522 | I79: 172.26 | J79: =SUMIFS($E$2:$E$201,$A$2:$A$201,A79) -> 7813.59 | K79: =IF(INDEX('Pivot Table'!$N$5:$N$34,MATCH(A79,'Pivot Table'!$I$5:$I$34,0))<=10,"Top 10","") -> Top 10 | L79: =ROUND(E79/(1-G79),2) -> 545.34 | M79: =ROUND(L79*(1-$U$3),2) -> 490.81 | N79: =ROUND(M79-(E79-I79),2) -> 145 | O79: =I79/E79 -> 0.33250333 | P79: =DATE(YEAR(H79),MONTH(H79),1) -> 45505 | Q79: =IF(J79>='Pivot Table'!$R$4,"High Value","Standard") -> Standard | R79: =NOW() -> 46304.64 | AD79: 17 | AE79: 306.87265 | AF79: -8.4926476 | AG79: -0.098678086
A80: CUST026 | B80: Linda Wilson | C80: West | D80: Office Supplies | E80: 1111.34 | F80: 1 | G80: 0 | H80: 45523 | I80: 500.1 | J80: =SUMIFS($E$2:$E$201,$A$2:$A$201,A80) -> 9371.81 | K80: =IF(INDEX('Pivot Table'!$N$5:$N$34,MATCH(A80,'Pivot Table'!$I$5:$I$34,0))<=10,"Top 10","") -> Top 10 | L80: =ROUND(E80/(1-G80),2) -> 1111.34 | M80: =ROUND(L80*(1-$U$3),2) -> 1000.21 | N80: =ROUND(M80-(E80-I80),2) -> 388.97 | O80: =I80/E80 -> 0.4499973 | P80: =DATE(YEAR(H80),MONTH(H80),1) -> 45505 | Q80: =IF(J80>='Pivot Table'!$R$4,"High Value","Standard") -> High Value | R80: =NOW() -> 46304.64 | T80: PREDICTION (uses the ToolPak coefficients above) | AD80: 18 | AE80: 222.35846 | AF80: -18.618457 | AG80: -0.21633227
A81: CUST030 | B81: Mary Davis | C81: East | D81: Clothing | E81: 1291.47 | F81: 18 | G81: 0.1 | H81: 45526 | I81: 581.16 | J81: =SUMIFS($E$2:$E$201,$A$2:$A$201,A81) -> 7928.71 | K81: =IF(INDEX('Pivot Table'!$N$5:$N$34,MATCH(A81,'Pivot Table'!$I$5:$I$34,0))<=10,"Top 10","") -> Top 10 | L81: =ROUND(E81/(1-G81),2) -> 1434.97 | M81: =ROUND(L81*(1-$U$3),2) -> 1291.47 | N81: =ROUND(M81-(E81-I81),2) -> 581.16 | O81: =I81/E81 -> 0.44999884 | P81: =DATE(YEAR(H81),MONTH(H81),1) -> 45505 | Q81: =IF(J81>='Pivot Table'!$R$4,"High Value","Standard") -> Standard | R81: =NOW() -> 46304.64 | T81: Sales amount (enter) | U81: 1000 | AD81: 19 | AE81: 527.40669 | AF81: -45.446688 | AG81: -0.52805584
A82: CUST007 | B82: David Brown | C82: North | D82: Books | E82: 679.71 | F82: 19 | G82: 0 | H82: 45534 | I82: 271.88 | J82: =SUMIFS($E$2:$E$201,$A$2:$A$201,A82) -> 9941.88 | K82: =IF(INDEX('Pivot Table'!$N$5:$N$34,MATCH(A82,'Pivot Table'!$I$5:$I$34,0))<=10,"Top 10","") -> Top 10 | L82: =ROUND(E82/(1-G82),2) -> 679.71 | M82: =ROUND(L82*(1-$U$3),2) -> 611.74 | N82: =ROUND(M82-(E82-I82),2) -> 203.91 | O82: =I82/E82 -> 0.39999412 | P82: =DATE(YEAR(H82),MONTH(H82),1) -> 45505 | Q82: =IF(J82>='Pivot Table'!$R$4,"High Value","Standard") -> High Value | R82: =NOW() -> 46304.64 | T82: Predicted Profit = Intercept + Slope × Sales | U82: =U76+U77*U81 -> 349.82444 | AD82: 20 | AE82: 225.27758 | AF82: -64.017579 | AG82: -0.74383543
A83: CUST020 | B83: Linda Jackson | C83: East | D83: Furniture | E83: 1143.69 | F83: 17 | G83: 0 | H83: 45534 | I83: 400.29 | J83: =SUMIFS($E$2:$E$201,$A$2:$A$201,A83) -> 4413.71 | K83: =IF(INDEX('Pivot Table'!$N$5:$N$34,MATCH(A83,'Pivot Table'!$I$5:$I$34,0))<=10,"Top 10","") | L83: =ROUND(E83/(1-G83),2) -> 1143.69 | M83: =ROUND(L83*(1-$U$3),2) -> 1029.32 | N83: =ROUND(M83-(E83-I83),2) -> 285.92 | O83: =I83/E83 -> 0.34999869 | P83: =DATE(YEAR(H83),MONTH(H83),1) -> 45505 | Q83: =IF(J83>='Pivot Table'!$R$4,"High Value","Standard") -> Standard | R83: =NOW() -> 46304.64 | AD83: 21 | AE83: 333.43946 | AF83: 143.21054 | AG83: 1.6639972
A84: CUST028 | B84: Linda Brown | C84: Central | D84: Electronics | E84: 790.08 | F84: 7 | G84: 0.1 | H84: 45536 | I84: 177.77 | J84: =SUMIFS($E$2:$E$201,$A$2:$A$201,A84) -> 10293.87 | K84: =IF(INDEX('Pivot Table'!$N$5:$N$34,MATCH(A84,'Pivot Table'!$I$5:$I$34,0))<=10,"Top 10","") -> Top 10 | L84: =ROUND(E84/(1-G84),2) -> 877.87 | M84: =ROUND(L84*(1-$U$3),2) -> 790.08 | N84: =ROUND(M84-(E84-I84),2) -> 177.77 | O84: =I84/E84 -> 0.22500253 | P84: =DATE(YEAR(H84),MONTH(H84),1) -> 45536 | Q84: =IF(J84>='Pivot Table'!$R$4,"High Value","Standard") -> High Value | R84: =NOW() -> 46304.64 | AD84: 22 | AE84: 135.29705 | AF84: -52.727052 | AG84: -0.61264812
A85: CUST005 | B85: Lisa Davis | C85: Central | D85: Books | E85: 1070.68 | F85: 7 | G85: 0.05 | H85: 45536 | I85: 406.86 | J85: =SUMIFS($E$2:$E$201,$A$2:$A$201,A85) -> 6666.13 | K85: =IF(INDEX('Pivot Table'!$N$5:$N$34,MATCH(A85,'Pivot Table'!$I$5:$I$34,0))<=10,"Top 10","") | L85: =ROUND(E85/(1-G85),2) -> 1127.03 | M85: =ROUND(L85*(1-$U$3),2) -> 1014.33 | N85: =ROUND(M85-(E85-I85),2) -> 350.51 | O85: =I85/E85 -> 0.38000149 | P85: =DATE(YEAR(H85),MONTH(H85),1) -> 45536 | Q85: =IF(J85>='Pivot Table'!$R$4,"High Value","Standard") -> Standard | R85: =NOW() -> 46304.64 | T85: HISTOGRAM – ToolPak-format output (Sales, bins 400 → 2,000) | AD85: 23 | AE85: 259.71409 | AF85: 37.555906 | AG85: 0.43637097
A86: CUST015 | B86: David Thomas | C86: West | D86: Clothing | E86: 1168.89 | F86: 4 | G86: 0.1 | H86: 45544 | I86: 526 | J86: =SUMIFS($E$2:$E$201,$A$2:$A$201,A86) -> 11611.06 | K86: =IF(INDEX('Pivot Table'!$N$5:$N$34,MATCH(A86,'Pivot Table'!$I$5:$I$34,0))<=10,"Top 10","") -> Top 10 | L86: =ROUND(E86/(1-G86),2) -> 1298.77 | M86: =ROUND(L86*(1-$U$3),2) -> 1168.89 | N86: =ROUND(M86-(E86-I86),2) -> 526 | O86: =I86/E86 -> 0.44999957 | P86: =DATE(YEAR(H86),MONTH(H86),1) -> 45536 | Q86: =IF(J86>='Pivot Table'!$R$4,"High Value","Standard") -> High Value | R86: =NOW() -> 46304.64 | T86: Bin | U86: Frequency | V86: Cumulative % | AD86: 24 | AE86: 246.80259 | AF86: -70.212594 | AG86: -0.81581677
A87: CUST003 | B87: James Davis | C87: South | D87: Electronics | E87: 1335.87 | F87: 17 | G87: 0 | H87: 45544 | I87: 333.97 | J87: =SUMIFS($E$2:$E$201,$A$2:$A$201,A87) -> 8490.18 | K87: =IF(INDEX('Pivot Table'!$N$5:$N$34,MATCH(A87,'Pivot Table'!$I$5:$I$34,0))<=10,"Top 10","") -> Top 10 | L87: =ROUND(E87/(1-G87),2) -> 1335.87 | M87: =ROUND(L87*(1-$U$3),2) -> 1202.28 | N87: =ROUND(M87-(E87-I87),2) -> 200.38 | O87: =I87/E87 -> 0.25000187 | P87: =DATE(YEAR(H87),MONTH(H87),1) -> 45536 | Q87: =IF(J87>='Pivot Table'!$R$4,"High Value","Standard") -> High Value | R87: =NOW() -> 46304.64 | T87: 400 | U87: 6 | V87: 0.03 | AD87: 25 | AE87: 323.619 | AF87: 51.130996 | AG87: 0.59410316
A88: CUST023 | B88: David Brown | C88: East | D88: Furniture | E88: 873.7 | F88: 9 | G88: 0 | H88: 45546 | I88: 305.8 | J88: =SUMIFS($E$2:$E$201,$A$2:$A$201,A88) -> 5913.68 | K88: =IF(INDEX('Pivot Table'!$N$5:$N$34,MATCH(A88,'Pivot Table'!$I$5:$I$34,0))<=10,"Top 10","") | L88: =ROUND(E88/(1-G88),2) -> 873.7 | M88: =ROUND(L88*(1-$U$3),2) -> 786.33 | N88: =ROUND(M88-(E88-I88),2) -> 218.43 | O88: =I88/E88 -> 0.35000572 | P88: =DATE(YEAR(H88),MONTH(H88),1) -> 45536 | Q88: =IF(J88>='Pivot Table'!$R$4,"High Value","Standard") -> Standard | R88: =NOW() -> 46304.64 | T88: 600 | U88: 16 | V88: 0.11 | AD88: 26 | AE88: 410.56463 | AF88: -117.28463 | AG88: -1.3627579
A89: CUST004 | B89: Sarah Davis | C89: West | D89: Office Supplies | E89: 1443.98 | F89: 19 | G89: 0 | H89: 45547 | I89: 649.79 | J89: =SUMIFS($E$2:$E$201,$A$2:$A$201,A89) -> 7813.59 | K89: =IF(INDEX('Pivot Table'!$N$5:$N$34,MATCH(A89,'Pivot Table'!$I$5:$I$34,0))<=10,"Top 10","") -> Top 10 | L89: =ROUND(E89/(1-G89),2) -> 1443.98 | M89: =ROUND(L89*(1-$U$3),2) -> 1299.58 | N89: =ROUND(M89-(E89-I89),2) -> 505.39 | O89: =I89/E89 -> 0.44999931 | P89: =DATE(YEAR(H89),MONTH(H89),1) -> 45536 | Q89: =IF(J89>='Pivot Table'!$R$4,"High Value","Standard") -> Standard | R89: =NOW() -> 46304.64 | T89: 800 | U89: 33 | V89: 0.275 | AD89: 27 | AE89: 235.9857 | AF89: 0.45429622 | AG89: 0.0052785755
A90: CUST023 | B90: James Wilson | C90: East | D90: Office Supplies | E90: 1154.33 | F90: 11 | G90: 0.15 | H90: 45549 | I90: 441.53 | J90: =SUMIFS($E$2:$E$201,$A$2:$A$201,A90) -> 5913.68 | K90: =IF(INDEX('Pivot Table'!$N$5:$N$34,MATCH(A90,'Pivot Table'!$I$5:$I$34,0))<=10,"Top 10","") | L90: =ROUND(E90/(1-G90),2) -> 1358.04 | M90: =ROUND(L90*(1-$U$3),2) -> 1222.24 | N90: =ROUND(M90-(E90-I90),2) -> 509.44 | O90: =I90/E90 -> 0.38249894 | P90: =DATE(YEAR(H90),MONTH(H90),1) -> 45536 | Q90: =IF(J90>='Pivot Table'!$R$4,"High Value","Standard") -> Standard | R90: =NOW() -> 46304.64 | T90: 1000 | U90: 51 | V90: 0.53 | AD90: 28 | AE90: 328.4538 | AF90: 28.396201 | AG90: 0.32994219
A91: CUST022 | B91: Linda Brown | C91: South | D91: Books | E91: 1264.49 | F91: 16 | G91: 0.05 | H91: 45549 | I91: 480.51 | J91: =SUMIFS($E$2:$E$201,$A$2:$A$201,A91) -> 4418.28 | K91: =IF(INDEX('Pivot Table'!$N$5:$N$34,MATCH(A91,'Pivot Table'!$I$5:$I$34,0))<=10,"Top 10","") | L91: =ROUND(E91/(1-G91),2) -> 1331.04 | M91: =ROUND(L91*(1-$U$3),2) -> 1197.94 | N91: =ROUND(M91-(E91-I91),2) -> 413.96 | O91: =I91/E91 -> 0.38000301 | P91: =DATE(YEAR(H91),MONTH(H91),1) -> 45536 | Q91: =IF(J91>='Pivot Table'!$R$4,"High Value","Standard") -> Standard | R91: =NOW() -> 46304.64 | T91: 1200 | U91: 50 | V91: 0.78 | AD91: 29 | AE91: 343.97918 | AF91: 54.270823 | AG91: 0.63058556
A92: CUST007 | B92: Emma Taylor | C92: West | D92: Furniture | E92: 1101.55 | F92: 4 | G92: 0.1 | H92: 45551 | I92: 346.99 | J92: =SUMIFS($E$2:$E$201,$A$2:$A$201,A92) -> 9941.88 | K92: =IF(INDEX('Pivot Table'!$N$5:$N$34,MATCH(A92,'Pivot Table'!$I$5:$I$34,0))<=10,"Top 10","") -> Top 10 | L92: =ROUND(E92/(1-G92),2) -> 1223.94 | M92: =ROUND(L92*(1-$U$3),2) -> 1101.55 | N92: =ROUND(M92-(E92-I92),2) -> 346.99 | O92: =I92/E92 -> 0.31500159 | P92: =DATE(YEAR(H92),MONTH(H92),1) -> 45536 | Q92: =IF(J92>='Pivot Table'!$R$4,"High Value","Standard") -> High Value | R92: =NOW() -> 46304.64 | T92: 1400 | U92: 26 | V92: 0.91 | AD92: 30 | AE92: 280.07778 | AF92: -119.83778 | AG92: -1.3924235
A93: CUST013 | B93: Robert Anderson | C93: South | D93: Furniture | E93: 727.73 | F93: 1 | G93: 0.1 | H93: 45552 | I93: 229.23 | J93: =SUMIFS($E$2:$E$201,$A$2:$A$201,A93) -> 4162.44 | K93: =IF(INDEX('Pivot Table'!$N$5:$N$34,MATCH(A93,'Pivot Table'!$I$5:$I$34,0))<=10,"Top 10","") | L93: =ROUND(E93/(1-G93),2) -> 808.59 | M93: =ROUND(L93*(1-$U$3),2) -> 727.73 | N93: =ROUND(M93-(E93-I93),2) -> 229.23 | O93: =I93/E93 -> 0.3149932 | P93: =DATE(YEAR(H93),MONTH(H93),1) -> 45536 | Q93: =IF(J93>='Pivot Table'!$R$4,"High Value","Standard") -> Standard | R93: =NOW() -> 46304.64 | T93: 1600 | U93: 14 | V93: 0.98 | AD93: 31 | AE93: 507.95874 | AF93: -181.54874 | AG93: -2.1094579
A94: CUST027 | B94: Emma Davis | C94: East | D94: Office Supplies | E94: 875.41 | F94: 13 | G94: 0.15 | H94: 45552 | I94: 334.84 | J94: =SUMIFS($E$2:$E$201,$A$2:$A$201,A94) -> 3906.04 | K94: =IF(INDEX('Pivot Table'!$N$5:$N$34,MATCH(A94,'Pivot Table'!$I$5:$I$34,0))<=10,"Top 10","") | L94: =ROUND(E94/(1-G94),2) -> 1029.89 | M94: =ROUND(L94*(1-$U$3),2) -> 926.9 | N94: =ROUND(M94-(E94-I94),2) -> 386.33 | O94: =I94/E94 -> 0.38249506 | P94: =DATE(YEAR(H94),MONTH(H94),1) -> 45536 | Q94: =IF(J94>='Pivot Table'!$R$4,"High Value","Standard") -> Standard | R94: =NOW() -> 46304.64 | T94: 1800 | U94: 3 | V94: 0.995 | AD94: 32 | AE94: 357.96781 | AF94: 30.852195 | AG94: 0.35847897
A95: CUST003 | B95: James Wilson | C95: West | D95: Electronics | E95: 1158.94 | F95: 19 | G95: 0.2 | H95: 45553 | I95: 231.79 | J95: =SUMIFS($E$2:$E$201,$A$2:$A$201,A95) -> 8490.18 | K95: =IF(INDEX('Pivot Table'!$N$5:$N$34,MATCH(A95,'Pivot Table'!$I$5:$I$34,0))<=10,"Top 10","") -> Top 10 | L95: =ROUND(E95/(1-G95),2) -> 1448.68 | M95: =ROUND(L95*(1-$U$3),2) -> 1303.81 | N95: =ROUND(M95-(E95-I95),2) -> 376.66 | O95: =I95/E95 -> 0.20000173 | P95: =DATE(YEAR(H95),MONTH(H95),1) -> 45536 | Q95: =IF(J95>='Pivot Table'!$R$4,"High Value","Standard") -> High Value | R95: =NOW() -> 46304.64 | T95: 2000 | U95: 1 | V95: 1 | AD95: 33 | AE95: 298.50122 | AF95: -44.521224 | AG95: -0.51730265
A96: CUST018 | B96: Mary Jackson | C96: South | D96: Books | E96: 966.3 | F96: 2 | G96: 0.15 | H96: 45557 | I96: 328.54 | J96: =SUMIFS($E$2:$E$201,$A$2:$A$201,A96) -> 4951.89 | K96: =IF(INDEX('Pivot Table'!$N$5:$N$34,MATCH(A96,'Pivot Table'!$I$5:$I$34,0))<=10,"Top 10","") | L96: =ROUND(E96/(1-G96),2) -> 1136.82 | M96: =ROUND(L96*(1-$U$3),2) -> 1023.14 | N96: =ROUND(M96-(E96-I96),2) -> 385.38 | O96: =I96/E96 -> 0.33999793 | P96: =DATE(YEAR(H96),MONTH(H96),1) -> 45536 | Q96: =IF(J96>='Pivot Table'!$R$4,"High Value","Standard") -> Standard | R96: =NOW() -> 46304.64 | T96: More | U96: 0 | V96: 1 | AD96: 34 | AE96: 338.55845 | AF96: -120.77845 | AG96: -1.4033535
A97: CUST020 | B97: James Taylor | C97: South | D97: Books | E97: 917.48 | F97: 6 | G97: 0 | H97: 45558 | I97: 366.99 | J97: =SUMIFS($E$2:$E$201,$A$2:$A$201,A97) -> 4413.71 | K97: =IF(INDEX('Pivot Table'!$N$5:$N$34,MATCH(A97,'Pivot Table'!$I$5:$I$34,0))<=10,"Top 10","") | L97: =ROUND(E97/(1-G97),2) -> 917.48 | M97: =ROUND(L97*(1-$U$3),2) -> 825.73 | N97: =ROUND(M97-(E97-I97),2) -> 275.24 | O97: =I97/E97 -> 0.39999782 | P97: =DATE(YEAR(H97),MONTH(H97),1) -> 45536 | Q97: =IF(J97>='Pivot Table'!$R$4,"High Value","Standard") -> Standard | R97: =NOW() -> 46304.64 | AD97: 35 | AE97: 420.31141 | AF97: 93.068594 | AG97: 1.0813861
A98: CUST029 | B98: Emma Wilson | C98: West | D98: Furniture | E98: 1172.97 | F98: 7 | G98: 0.15 | H98: 45559 | I98: 348.96 | J98: =SUMIFS($E$2:$E$201,$A$2:$A$201,A98) -> 5779.05 | K98: =IF(INDEX('Pivot Table'!$N$5:$N$34,MATCH(A98,'Pivot Table'!$I$5:$I$34,0))<=10,"Top 10","") | L98: =ROUND(E98/(1-G98),2) -> 1379.96 | M98: =ROUND(L98*(1-$U$3),2) -> 1241.96 | N98: =ROUND(M98-(E98-I98),2) -> 417.95 | O98: =I98/E98 -> 0.29750121 | P98: =DATE(YEAR(H98),MONTH(H98),1) -> 45536 | Q98: =IF(J98>='Pivot Table'!$R$4,"High Value","Standard") -> Standard | R98: =NOW() -> 46304.64 | AD98: 36 | AE98: 164.7058 | AF98: -13.545801 | AG98: -0.15739188
A99: CUST021 | B99: James Wilson | C99: North | D99: Clothing | E99: 1205.82 | F99: 11 | G99: 0.1 | H99: 45559 | I99: 542.62 | J99: =SUMIFS($E$2:$E$201,$A$2:$A$201,A99) -> 8740.18 | K99: =IF(INDEX('Pivot Table'!$N$5:$N$34,MATCH(A99,'Pivot Table'!$I$5:$I$34,0))<=10,"Top 10","") -> Top 10 | L99: =ROUND(E99/(1-G99),2) -> 1339.8 | M99: =ROUND(L99*(1-$U$3),2) -> 1205.82 | N99: =ROUND(M99-(E99-I99),2) -> 542.62 | O99: =I99/E99 -> 0.45000083 | P99: =DATE(YEAR(H99),MONTH(H99),1) -> 45536 | Q99: =IF(J99>='Pivot Table'!$R$4,"High Value","Standard") -> High Value | R99: =NOW() -> 46304.64 | AD99: 37 | AE99: 294.01027 | AF99: 65.479733 | AG99: 0.76082454
A100: CUST017 | B100: Sarah Davis | C100: West | D100: Office Supplies | E100: 826.93 | F100: 10 | G100: 0.2 | H100: 45564 | I100: 297.69 | J100: =SUMIFS($E$2:$E$201,$A$2:$A$201,A100) -> 3419.2 | K100: =IF(INDEX('Pivot Table'!$N$5:$N$34,MATCH(A100,'Pivot Table'!$I$5:$I$34,0))<=10,"Top 10","") | L100: =ROUND(E100/(1-G100),2) -> 1033.66 | M100: =ROUND(L100*(1-$U$3),2) -> 930.29 | N100: =ROUND(M100-(E100-I100),2) -> 401.05 | O100: =I100/E100 -> 0.3599942 | P100: =DATE(YEAR(H100),MONTH(H100),1) -> 45536 | Q100: =IF(J100>='Pivot Table'!$R$4,"High Value","Standard") -> Standard | R100: =NOW() -> 46304.64 | AD100: 38 | AE100: 493.69644 | AF100: -24.856444 | AG100: -0.28881292
A101: CUST003 | B101: James Wilson | C101: Central | D101: Clothing | E101: 902.19 | F101: 12 | G101: 0 | H101: 45564 | I101: 451.1 | J101: =SUMIFS($E$2:$E$201,$A$2:$A$201,A101) -> 8490.18 | K101: =IF(INDEX('Pivot Table'!$N$5:$N$34,MATCH(A101,'Pivot Table'!$I$5:$I$34,0))<=10,"Top 10","") -> Top 10 | L101: =ROUND(E101/(1-G101),2) -> 902.19 | M101: =ROUND(L101*(1-$U$3),2) -> 811.97 | N101: =ROUND(M101-(E101-I101),2) -> 360.88 | O101: =I101/E101 -> 0.50000554 | P101: =DATE(YEAR(H101),MONTH(H101),1) -> 45536 | Q101: =IF(J101>='Pivot Table'!$R$4,"High Value","Standard") -> High Value | R101: =NOW() -> 46304.64 | AD101: 39 | AE101: 270.21171 | AF101: -40.221705 | AG101: -0.46734553
A102: CUST027 | B102: Emma Davis | C102: North | D102: Books | E102: 585.97 | F102: 17 | G102: 0.1 | H102: 45565 | I102: 210.95 | J102: =SUMIFS($E$2:$E$201,$A$2:$A$201,A102) -> 3906.04 | K102: =IF(INDEX('Pivot Table'!$N$5:$N$34,MATCH(A102,'Pivot Table'!$I$5:$I$34,0))<=10,"Top 10","") | L102: =ROUND(E102/(1-G102),2) -> 651.08 | M102: =ROUND(L102*(1-$U$3),2) -> 585.97 | N102: =ROUND(M102-(E102-I102),2) -> 210.95 | O102: =I102/E102 -> 0.36000137 | P102: =DATE(YEAR(H102),MONTH(H102),1) -> 45536 | Q102: =IF(J102>='Pivot Table'!$R$4,"High Value","Standard") -> Standard | R102: =NOW() -> 46304.64 | AD102: 40 | AE102: 202.61579 | AF102: -5.2657907 | AG102: -0.061184471
A103: CUST016 | B103: Michael Anderson | C103: North | D103: Clothing | E103: 990.19 | F103: 8 | G103: 0.1 | H103: 45565 | I103: 445.59 | J103: =SUMIFS($E$2:$E$201,$A$2:$A$201,A103) -> 3369.17 | K103: =IF(INDEX('Pivot Table'!$N$5:$N$34,MATCH(A103,'Pivot Table'!$I$5:$I$34,0))<=10,"Top 10","") | L103: =ROUND(E103/(1-G103),2) -> 1100.21 | M103: =ROUND(L103*(1-$U$3),2) -> 990.19 | N103: =ROUND(M103-(E103-I103),2) -> 445.59 | O103: =I103/E103 -> 0.45000454 | P103: =DATE(YEAR(H103),MONTH(H103),1) -> 45536 | Q103: =IF(J103>='Pivot Table'!$R$4,"High Value","Standard") -> Standard | R103: =NOW() -> 46304.64 | AD103: 41 | AE103: 402.87737 | AF103: 11.562628 | AG103: 0.13434892
A104: CUST008 | B104: David Davis | C104: Central | D104: Electronics | E104: 1014.09 | F104: 13 | G104: 0.2 | H104: 45567 | I104: 202.82 | J104: =SUMIFS($E$2:$E$201,$A$2:$A$201,A104) -> 9760.8 | K104: =IF(INDEX('Pivot Table'!$N$5:$N$34,MATCH(A104,'Pivot Table'!$I$5:$I$34,0))<=10,"Top 10","") -> Top 10 | L104: =ROUND(E104/(1-G104),2) -> 1267.61 | M104: =ROUND(L104*(1-$U$3),2) -> 1140.85 | N104: =ROUND(M104-(E104-I104),2) -> 329.58 | O104: =I104/E104 -> 0.20000197 | P104: =DATE(YEAR(H104),MONTH(H104),1) -> 45566 | Q104: =IF(J104>='Pivot Table'!$R$4,"High Value","Standard") -> High Value | R104: =NOW() -> 46304.64 | AD104: 42 | AE104: 358.93968 | AF104: 10.410324 | AG104: 0.12096002
A105: CUST012 | B105: Lisa Davis | C105: North | D105: Electronics | E105: 925.29 | F105: 17 | G105: 0 | H105: 45570 | I105: 231.32 | J105: =SUMIFS($E$2:$E$201,$A$2:$A$201,A105) -> 8339 | K105: =IF(INDEX('Pivot Table'!$N$5:$N$34,MATCH(A105,'Pivot Table'!$I$5:$I$34,0))<=10,"Top 10","") -> Top 10 | L105: =ROUND(E105/(1-G105),2) -> 925.29 | M105: =ROUND(L105*(1-$U$3),2) -> 832.76 | N105: =ROUND(M105-(E105-I105),2) -> 138.79 | O105: =I105/E105 -> 0.2499973 | P105: =DATE(YEAR(H105),MONTH(H105),1) -> 45566 | Q105: =IF(J105>='Pivot Table'!$R$4,"High Value","Standard") -> High Value | R105: =NOW() -> 46304.64 | AD105: 43 | AE105: 194.19174 | AF105: 18.638262 | AG105: 0.21656238
A106: CUST025 | B106: Mary Jackson | C106: East | D106: Furniture | E106: 1286.54 | F106: 8 | G106: 0 | H106: 45575 | I106: 450.29 | J106: =SUMIFS($E$2:$E$201,$A$2:$A$201,A106) -> 6716.52 | K106: =IF(INDEX('Pivot Table'!$N$5:$N$34,MATCH(A106,'Pivot Table'!$I$5:$I$34,0))<=10,"Top 10","") | L106: =ROUND(E106/(1-G106),2) -> 1286.54 | M106: =ROUND(L106*(1-$U$3),2) -> 1157.89 | N106: =ROUND(M106-(E106-I106),2) -> 321.64 | O106: =I106/E106 -> 0.35000078 | P106: =DATE(YEAR(H106),MONTH(H106),1) -> 45566 | Q106: =IF(J106>='Pivot Table'!$R$4,"High Value","Standard") -> Standard | R106: =NOW() -> 46304.64 | AD106: 44 | AE106: 293.98571 | AF106: 8.7242928 | AG106: 0.10136963
...

Sheet Pivot Table
A1: PIVOT TABLES – SALES ANALYSIS
A3: 1. TOTAL SALES BY REGION × PRODUCT CATEGORY | I3: 5. CUSTOMER ANALYSIS (SUMIFS group-by + INDEX/MATCH) | Q3: 6. HIGH-VALUE CUSTOMERS (INDEX / MATCH)
A4: Region | B4: Books | C4: Clothing | D4: Electronics | E4: Furniture | F4: Office Supplies | G4: Grand Total | I4: Customer ID | J4: Name (first recorded) | K4: Orders | L4: Total Sales | M4: Total Profit | N4: Rank | O4: Tier | Q4: High-value threshold (75th percentile of Total Sales) | R4: =ROUND(PERCENTILE($L$5:$L$34,0.75),2) -> 8236.43
A5: Central | B5: =SUMIFS(Dataset!$E$2:$E$201,Dataset!$C$2:$C$201,$A5,Dataset!$D$2:$D$201,B$4) -> 11297.15 | C5: =SUMIFS(Dataset!$E$2:$E$201,Dataset!$C$2:$C$201,$A5,Dataset!$D$2:$D$201,C$4) -> 12200.26 | D5: =SUMIFS(Dataset!$E$2:$E$201,Dataset!$C$2:$C$201,$A5,Dataset!$D$2:$D$201,D$4) -> 6621.24 | E5: =SUMIFS(Dataset!$E$2:$E$201,Dataset!$C$2:$C$201,$A5,Dataset!$D$2:$D$201,E$4) -> 4876.96 | F5: =SUMIFS(Dataset!$E$2:$E$201,Dataset!$C$2:$C$201,$A5,Dataset!$D$2:$D$201,F$4) -> 8472.72 | G5: =SUM(B5:F5) -> 43468.33 | I5: CUST001 | J5: =INDEX(Dataset!$B$2:$B$201,MATCH(I5,Dataset!$A$2:$A$201,0)) -> Linda Wilson | K5: =COUNTIFS(Dataset!$A$2:$A$201,I5) -> 7 | L5: =SUMIFS(Dataset!$E$2:$E$201,Dataset!$A$2:$A$201,I5) -> 6549.55 | M5: =SUMIFS(Dataset!$I$2:$I$201,Dataset!$A$2:$A$201,I5) -> 1868.77 | N5: =RANK(L5,$L$5:$L$34)+COUNTIF($L$5:L5,L5)-1 -> 15 | O5: =IF(L5>=$R$4,"High Value","Standard") -> Standard | Q5: Number of high-value customers | R5: =COUNTIF($O$5:$O$34,"High Value") -> 8
A6: East | B6: =SUMIFS(Dataset!$E$2:$E$201,Dataset!$C$2:$C$201,$A6,Dataset!$D$2:$D$201,B$4) -> 11389.09 | C6: =SUMIFS(Dataset!$E$2:$E$201,Dataset!$C$2:$C$201,$A6,Dataset!$D$2:$D$201,C$4) -> 2401.45 | D6: =SUMIFS(Dataset!$E$2:$E$201,Dataset!$C$2:$C$201,$A6,Dataset!$D$2:$D$201,D$4) -> 2869.54 | E6: =SUMIFS(Dataset!$E$2:$E$201,Dataset!$C$2:$C$201,$A6,Dataset!$D$2:$D$201,E$4) -> 7592.34 | F6: =SUMIFS(Dataset!$E$2:$E$201,Dataset!$C$2:$C$201,$A6,Dataset!$D$2:$D$201,F$4) -> 8189.22 | G6: =SUM(B6:F6) -> 32441.64 | I6: CUST002 | J6: =INDEX(Dataset!$B$2:$B$201,MATCH(I6,Dataset!$A$2:$A$201,0)) -> Lisa Davis | K6: =COUNTIFS(Dataset!$A$2:$A$201,I6) -> 6 | L6: =SUMIFS(Dataset!$E$2:$E$201,Dataset!$A$2:$A$201,I6) -> 6481.43 | M6: =SUMIFS(Dataset!$I$2:$I$201,Dataset!$A$2:$A$201,I6) -> 2210.74 | N6: =RANK(L6,$L$5:$L$34)+COUNTIF($L$5:L6,L6)-1 -> 17 | O6: =IF(L6>=$R$4,"High Value","Standard") -> Standard | Q6: Rank | R6: Customer ID | S6: Name (first recorded) | T6: Total Sales | U6: Total Profit
A7: North | B7: =SUMIFS(Dataset!$E$2:$E$201,Dataset!$C$2:$C$201,$A7,Dataset!$D$2:$D$201,B$4) -> 8037.01 | C7: =SUMIFS(Dataset!$E$2:$E$201,Dataset!$C$2:$C$201,$A7,Dataset!$D$2:$D$201,C$4) -> 8422.82 | D7: =SUMIFS(Dataset!$E$2:$E$201,Dataset!$C$2:$C$201,$A7,Dataset!$D$2:$D$201,D$4) -> 8191.71 | E7: =SUMIFS(Dataset!$E$2:$E$201,Dataset!$C$2:$C$201,$A7,Dataset!$D$2:$D$201,E$4) -> 6978.08 | F7: =SUMIFS(Dataset!$E$2:$E$201,Dataset!$C$2:$C$201,$A7,Dataset!$D$2:$D$201,F$4) -> 3345.8 | G7: =SUM(B7:F7) -> 34975.42 | I7: CUST003 | J7: =INDEX(Dataset!$B$2:$B$201,MATCH(I7,Dataset!$A$2:$A$201,0)) -> Emma Davis | K7: =COUNTIFS(Dataset!$A$2:$A$201,I7) -> 9 | L7: =SUMIFS(Dataset!$E$2:$E$201,Dataset!$A$2:$A$201,I7) -> 8490.18 | M7: =SUMIFS(Dataset!$I$2:$I$201,Dataset!$A$2:$A$201,I7) -> 2652.75 | N7: =RANK(L7,$L$5:$L$34)+COUNTIF($L$5:L7,L7)-1 -> 7 | O7: =IF(L7>=$R$4,"High Value","Standard") -> High Value | Q7: =IF(ROWS(Q$7:Q7)<=$R$5,ROWS(Q$7:Q7),"") -> 1 | R7: =IF($Q7="","",INDEX($I$5:$I$34,MATCH($Q7,$N$5:$N$34,0))) -> CUST015 | S7: =IF($Q7="","",INDEX($J$5:$J$34,MATCH($Q7,$N$5:$N$34,0))) -> Linda Taylor | T7: =IF($Q7="","",INDEX($L$5:$L$34,MATCH($Q7,$N$5:$N$34,0))) -> 11611.06 | U7: =IF($Q7="","",INDEX($M$5:$M$34,MATCH($Q7,$N$5:$N$34,0))) -> 4201.59
A8: South | B8: =SUMIFS(Dataset!$E$2:$E$201,Dataset!$C$2:$C$201,$A8,Dataset!$D$2:$D$201,B$4) -> 9588.04 | C8: =SUMIFS(Dataset!$E$2:$E$201,Dataset!$C$2:$C$201,$A8,Dataset!$D$2:$D$201,C$4) -> 8393.63 | D8: =SUMIFS(Dataset!$E$2:$E$201,Dataset!$C$2:$C$201,$A8,Dataset!$D$2:$D$201,D$4) -> 11989.07 | E8: =SUMIFS(Dataset!$E$2:$E$201,Dataset!$C$2:$C$201,$A8,Dataset!$D$2:$D$201,E$4) -> 7982.73 | F8: =SUMIFS(Dataset!$E$2:$E$201,Dataset!$C$2:$C$201,$A8,Dataset!$D$2:$D$201,F$4) -> 2295.32 | G8: =SUM(B8:F8) -> 40248.79 | I8: CUST004 | J8: =INDEX(Dataset!$B$2:$B$201,MATCH(I8,Dataset!$A$2:$A$201,0)) -> Lisa Thomas | K8: =COUNTIFS(Dataset!$A$2:$A$201,I8) -> 7 | L8: =SUMIFS(Dataset!$E$2:$E$201,Dataset!$A$2:$A$201,I8) -> 7813.59 | M8: =SUMIFS(Dataset!$I$2:$I$201,Dataset!$A$2:$A$201,I8) -> 3211.82 | N8: =RANK(L8,$L$5:$L$34)+COUNTIF($L$5:L8,L8)-1 -> 10 | O8: =IF(L8>=$R$4,"High Value","Standard") -> Standard | Q8: =IF(ROWS(Q$7:Q8)<=$R$5,ROWS(Q$7:Q8),"") -> 2 | R8: =IF($Q8="","",INDEX($I$5:$I$34,MATCH($Q8,$N$5:$N$34,0))) -> CUST028 | S8: =IF($Q8="","",INDEX($J$5:$J$34,MATCH($Q8,$N$5:$N$34,0))) -> Linda Taylor | T8: =IF($Q8="","",INDEX($L$5:$L$34,MATCH($Q8,$N$5:$N$34,0))) -> 10293.87 | U8: =IF($Q8="","",INDEX($M$5:$M$34,MATCH($Q8,$N$5:$N$34,0))) -> 3541.02
A9: West | B9: =SUMIFS(Dataset!$E$2:$E$201,Dataset!$C$2:$C$201,$A9,Dataset!$D$2:$D$201,B$4) -> 6691.17 | C9: =SUMIFS(Dataset!$E$2:$E$201,Dataset!$C$2:$C$201,$A9,Dataset!$D$2:$D$201,C$4) -> 10509.43 | D9: =SUMIFS(Dataset!$E$2:$E$201,Dataset!$C$2:$C$201,$A9,Dataset!$D$2:$D$201,D$4) -> 11372.44 | E9: =SUMIFS(Dataset!$E$2:$E$201,Dataset!$C$2:$C$201,$A9,Dataset!$D$2:$D$201,E$4) -> 9182.78 | F9: =SUMIFS(Dataset!$E$2:$E$201,Dataset!$C$2:$C$201,$A9,Dataset!$D$2:$D$201,F$4) -> 6327.76 | G9: =SUM(B9:F9) -> 44083.58 | I9: CUST005 | J9: =INDEX(Dataset!$B$2:$B$201,MATCH(I9,Dataset!$A$2:$A$201,0)) -> Robert Anderson | K9: =COUNTIFS(Dataset!$A$2:$A$201,I9) -> 6 | L9: =SUMIFS(Dataset!$E$2:$E$201,Dataset!$A$2:$A$201,I9) -> 6666.13 | M9: =SUMIFS(Dataset!$I$2:$I$201,Dataset!$A$2:$A$201,I9) -> 1982.39 | N9: =RANK(L9,$L$5:$L$34)+COUNTIF($L$5:L9,L9)-1 -> 14 | O9: =IF(L9>=$R$4,"High Value","Standard") -> Standard | Q9: =IF(ROWS(Q$7:Q9)<=$R$5,ROWS(Q$7:Q9),"") -> 3 | R9: =IF($Q9="","",INDEX($I$5:$I$34,MATCH($Q9,$N$5:$N$34,0))) -> CUST007 | S9: =IF($Q9="","",INDEX($J$5:$J$34,MATCH($Q9,$N$5:$N$34,0))) -> Michael Anderson | T9: =IF($Q9="","",INDEX($L$5:$L$34,MATCH($Q9,$N$5:$N$34,0))) -> 9941.88 | U9: =IF($Q9="","",INDEX($M$5:$M$34,MATCH($Q9,$N$5:$N$34,0))) -> 3936.26
A10: Grand Total | B10: =SUM(B5:B9) -> 47002.46 | C10: =SUM(C5:C9) -> 41927.59 | D10: =SUM(D5:D9) -> 41044 | E10: =SUM(E5:E9) -> 36612.89 | F10: =SUM(F5:F9) -> 28630.82 | G10: =SUM(G5:G9) -> 195217.76 | I10: CUST006 | J10: =INDEX(Dataset!$B$2:$B$201,MATCH(I10,Dataset!$A$2:$A$201,0)) -> Mary Jackson | K10: =COUNTIFS(Dataset!$A$2:$A$201,I10) -> 2 | L10: =SUMIFS(Dataset!$E$2:$E$201,Dataset!$A$2:$A$201,I10) -> 2699.75 | M10: =SUMIFS(Dataset!$I$2:$I$201,Dataset!$A$2:$A$201,I10) -> 837.06 | N10: =RANK(L10,$L$5:$L$34)+COUNTIF($L$5:L10,L10)-1 -> 30 | O10: =IF(L10>=$R$4,"High Value","Standard") -> Standard | Q10: =IF(ROWS(Q$7:Q10)<=$R$5,ROWS(Q$7:Q10),"") -> 4 | R10: =IF($Q10="","",INDEX($I$5:$I$34,MATCH($Q10,$N$5:$N$34,0))) -> CUST008 | S10: =IF($Q10="","",INDEX($J$5:$J$34,MATCH($Q10,$N$5:$N$34,0))) -> Robert Anderson | T10: =IF($Q10="","",INDEX($L$5:$L$34,MATCH($Q10,$N$5:$N$34,0))) -> 9760.8 | U10: =IF($Q10="","",INDEX($M$5:$M$34,MATCH($Q10,$N$5:$N$34,0))) -> 3442.48
I11: CUST007 | J11: =INDEX(Dataset!$B$2:$B$201,MATCH(I11,Dataset!$A$2:$A$201,0)) -> Michael Anderson | K11: =COUNTIFS(Dataset!$A$2:$A$201,I11) -> 10 | L11: =SUMIFS(Dataset!$E$2:$E$201,Dataset!$A$2:$A$201,I11) -> 9941.88 | M11: =SUMIFS(Dataset!$I$2:$I$201,Dataset!$A$2:$A$201,I11) -> 3936.26 | N11: =RANK(L11,$L$5:$L$34)+COUNTIF($L$5:L11,L11)-1 -> 3 | O11: =IF(L11>=$R$4,"High Value","Standard") -> High Value | Q11: =IF(ROWS(Q$7:Q11)<=$R$5,ROWS(Q$7:Q11),"") -> 5 | R11: =IF($Q11="","",INDEX($I$5:$I$34,MATCH($Q11,$N$5:$N$34,0))) -> CUST026 | S11: =IF($Q11="","",INDEX($J$5:$J$34,MATCH($Q11,$N$5:$N$34,0))) -> Mary Davis | T11: =IF($Q11="","",INDEX($L$5:$L$34,MATCH($Q11,$N$5:$N$34,0))) -> 9371.81 | U11: =IF($Q11="","",INDEX($M$5:$M$34,MATCH($Q11,$N$5:$N$34,0))) -> 2922.02
I12: CUST008 | J12: =INDEX(Dataset!$B$2:$B$201,MATCH(I12,Dataset!$A$2:$A$201,0)) -> Robert Anderson | K12: =COUNTIFS(Dataset!$A$2:$A$201,I12) -> 10 | L12: =SUMIFS(Dataset!$E$2:$E$201,Dataset!$A$2:$A$201,I12) -> 9760.8 | M12: =SUMIFS(Dataset!$I$2:$I$201,Dataset!$A$2:$A$201,I12) -> 3442.48 | N12: =RANK(L12,$L$5:$L$34)+COUNTIF($L$5:L12,L12)-1 -> 4 | O12: =IF(L12>=$R$4,"High Value","Standard") -> High Value | Q12: =IF(ROWS(Q$7:Q12)<=$R$5,ROWS(Q$7:Q12),"") -> 6 | R12: =IF($Q12="","",INDEX($I$5:$I$34,MATCH($Q12,$N$5:$N$34,0))) -> CUST021 | S12: =IF($Q12="","",INDEX($J$5:$J$34,MATCH($Q12,$N$5:$N$34,0))) -> Sarah Anderson | T12: =IF($Q12="","",INDEX($L$5:$L$34,MATCH($Q12,$N$5:$N$34,0))) -> 8740.18 | U12: =IF($Q12="","",INDEX($M$5:$M$34,MATCH($Q12,$N$5:$N$34,0))) -> 2848.62
A13: 2. REGION SUMMARY | I13: CUST009 | J13: =INDEX(Dataset!$B$2:$B$201,MATCH(I13,Dataset!$A$2:$A$201,0)) -> Linda Jackson | K13: =COUNTIFS(Dataset!$A$2:$A$201,I13) -> 7 | L13: =SUMIFS(Dataset!$E$2:$E$201,Dataset!$A$2:$A$201,I13) -> 6505.2 | M13: =SUMIFS(Dataset!$I$2:$I$201,Dataset!$A$2:$A$201,I13) -> 2052.54 | N13: =RANK(L13,$L$5:$L$34)+COUNTIF($L$5:L13,L13)-1 -> 16 | O13: =IF(L13>=$R$4,"High Value","Standard") -> Standard | Q13: =IF(ROWS(Q$7:Q13)<=$R$5,ROWS(Q$7:Q13),"") -> 7 | R13: =IF($Q13="","",INDEX($I$5:$I$34,MATCH($Q13,$N$5:$N$34,0))) -> CUST003 | S13: =IF($Q13="","",INDEX($J$5:$J$34,MATCH($Q13,$N$5:$N$34,0))) -> Emma Davis | T13: =IF($Q13="","",INDEX($L$5:$L$34,MATCH($Q13,$N$5:$N$34,0))) -> 8490.18 | U13: =IF($Q13="","",INDEX($M$5:$M$34,MATCH($Q13,$N$5:$N$34,0))) -> 2652.75
A14: Region | B14: Orders | C14: Sales | D14: Profit | E14: Profit Margin | F14: Avg Discount | I14: CUST010 | J14: =INDEX(Dataset!$B$2:$B$201,MATCH(I14,Dataset!$A$2:$A$201,0)) -> David Thomas | K14: =COUNTIFS(Dataset!$A$2:$A$201,I14) -> 5 | L14: =SUMIFS(Dataset!$E$2:$E$201,Dataset!$A$2:$A$201,I14) -> 4259.22 | M14: =SUMIFS(Dataset!$I$2:$I$201,Dataset!$A$2:$A$201,I14) -> 1529.32 | N14: =RANK(L14,$L$5:$L$34)+COUNTIF($L$5:L14,L14)-1 -> 24 | O14: =IF(L14>=$R$4,"High Value","Standard") -> Standard | Q14: =IF(ROWS(Q$7:Q14)<=$R$5,ROWS(Q$7:Q14),"") -> 8 | R14: =IF($Q14="","",INDEX($I$5:$I$34,MATCH($Q14,$N$5:$N$34,0))) -> CUST012 | S14: =IF($Q14="","",INDEX($J$5:$J$34,MATCH($Q14,$N$5:$N$34,0))) -> Robert Anderson | T14: =IF($Q14="","",INDEX($L$5:$L$34,MATCH($Q14,$N$5:$N$34,0))) -> 8339 | U14: =IF($Q14="","",INDEX($M$5:$M$34,MATCH($Q14,$N$5:$N$34,0))) -> 2988.71
A15: Central | B15: =COUNTIFS(Dataset!$C$2:$C$201,$A15) -> 44 | C15: =SUMIFS(Dataset!$E$2:$E$201,Dataset!$C$2:$C$201,$A15) -> 43468.33 | D15: =SUMIFS(Dataset!$I$2:$I$201,Dataset!$C$2:$C$201,$A15) -> 16068.4 | E15: =D15/C15 -> 0.36965763 | F15: =AVERAGEIFS(Dataset!$G$2:$G$201,Dataset!$C$2:$C$201,$A15) -> 0.086363636 | I15: CUST011 | J15: =INDEX(Dataset!$B$2:$B$201,MATCH(I15,Dataset!$A$2:$A$201,0)) -> Mary Davis | K15: =COUNTIFS(Dataset!$A$2:$A$201,I15) -> 4 | L15: =SUMIFS(Dataset!$E$2:$E$201,Dataset!$A$2:$A$201,I15) -> 3762.29 | M15: =SUMIFS(Dataset!$I$2:$I$201,Dataset!$A$2:$A$201,I15) -> 1545.04 | N15: =RANK(L15,$L$5:$L$34)+COUNTIF($L$5:L15,L15)-1 -> 27 | O15: =IF(L15>=$R$4,"High Value","Standard") -> Standard | Q15: =IF(ROWS(Q$7:Q15)<=$R$5,ROWS(Q$7:Q15),"") | R15: =IF($Q15="","",INDEX($I$5:$I$34,MATCH($Q15,$N$5:$N$34,0))) | S15: =IF($Q15="","",INDEX($J$5:$J$34,MATCH($Q15,$N$5:$N$34,0))) | T15: =IF($Q15="","",INDEX($L$5:$L$34,MATCH($Q15,$N$5:$N$34,0))) | U15: =IF($Q15="","",INDEX($M$5:$M$34,MATCH($Q15,$N$5:$N$34,0)))
A16: East | B16: =COUNTIFS(Dataset!$C$2:$C$201,$A16) -> 32 | C16: =SUMIFS(Dataset!$E$2:$E$201,Dataset!$C$2:$C$201,$A16) -> 32441.64 | D16: =SUMIFS(Dataset!$I$2:$I$201,Dataset!$C$2:$C$201,$A16) -> 11638.59 | E16: =D16/C16 -> 0.35875467 | F16: =AVERAGEIFS(Dataset!$G$2:$G$201,Dataset!$C$2:$C$201,$A16) -> 0.0921875 | I16: CUST012 | J16: =INDEX(Dataset!$B$2:$B$201,MATCH(I16,Dataset!$A$2:$A$201,0)) -> Robert Anderson | K16: =COUNTIFS(Dataset!$A$2:$A$201,I16) -> 9 | L16: =SUMIFS(Dataset!$E$2:$E$201,Dataset!$A$2:$A$201,I16) -> 8339 | M16: =SUMIFS(Dataset!$I$2:$I$201,Dataset!$A$2:$A$201,I16) -> 2988.71 | N16: =RANK(L16,$L$5:$L$34)+COUNTIF($L$5:L16,L16)-1 -> 8 | O16: =IF(L16>=$R$4,"High Value","Standard") -> High Value | Q16: =IF(ROWS(Q$7:Q16)<=$R$5,ROWS(Q$7:Q16),"") | R16: =IF($Q16="","",INDEX($I$5:$I$34,MATCH($Q16,$N$5:$N$34,0))) | S16: =IF($Q16="","",INDEX($J$5:$J$34,MATCH($Q16,$N$5:$N$34,0))) | T16: =IF($Q16="","",INDEX($L$5:$L$34,MATCH($Q16,$N$5:$N$34,0))) | U16: =IF($Q16="","",INDEX($M$5:$M$34,MATCH($Q16,$N$5:$N$34,0)))
A17: North | B17: =COUNTIFS(Dataset!$C$2:$C$201,$A17) -> 39 | C17: =SUMIFS(Dataset!$E$2:$E$201,Dataset!$C$2:$C$201,$A17) -> 34975.42 | D17: =SUMIFS(Dataset!$I$2:$I$201,Dataset!$C$2:$C$201,$A17) -> 11902.28 | E17: =D17/C17 -> 0.34030413 | F17: =AVERAGEIFS(Dataset!$G$2:$G$201,Dataset!$C$2:$C$201,$A17) -> 0.11666667 | I17: CUST013 | J17: =INDEX(Dataset!$B$2:$B$201,MATCH(I17,Dataset!$A$2:$A$201,0)) -> Robert Anderson | K17: =COUNTIFS(Dataset!$A$2:$A$201,I17) -> 4 | L17: =SUMIFS(Dataset!$E$2:$E$201,Dataset!$A$2:$A$201,I17) -> 4162.44 | M17: =SUMIFS(Dataset!$I$2:$I$201,Dataset!$A$2:$A$201,I17) -> 1605.11 | N17: =RANK(L17,$L$5:$L$34)+COUNTIF($L$5:L17,L17)-1 -> 25 | O17: =IF(L17>=$R$4,"High Value","Standard") -> Standard
A18: South | B18: =COUNTIFS(Dataset!$C$2:$C$201,$A18) -> 42 | C18: =SUMIFS(Dataset!$E$2:$E$201,Dataset!$C$2:$C$201,$A18) -> 40248.79 | D18: =SUMIFS(Dataset!$I$2:$I$201,Dataset!$C$2:$C$201,$A18) -> 13691.91 | E18: =D18/C18 -> 0.3401819 | F18: =AVERAGEIFS(Dataset!$G$2:$G$201,Dataset!$C$2:$C$201,$A18) -> 0.079761905 | I18: CUST014 | J18: =INDEX(Dataset!$B$2:$B$201,MATCH(I18,Dataset!$A$2:$A$201,0)) -> Emma Davis | K18: =COUNTIFS(Dataset!$A$2:$A$201,I18) -> 6 | L18: =SUMIFS(Dataset!$E$2:$E$201,Dataset!$A$2:$A$201,I18) -> 6729.89 | M18: =SUMIFS(Dataset!$I$2:$I$201,Dataset!$A$2:$A$201,I18) -> 2507.18 | N18: =RANK(L18,$L$5:$L$34)+COUNTIF($L$5:L18,L18)-1 -> 12 | O18: =IF(L18>=$R$4,"High Value","Standard") -> Standard
A19: West | B19: =COUNTIFS(Dataset!$C$2:$C$201,$A19) -> 43 | C19: =SUMIFS(Dataset!$E$2:$E$201,Dataset!$C$2:$C$201,$A19) -> 44083.58 | D19: =SUMIFS(Dataset!$I$2:$I$201,Dataset!$C$2:$C$201,$A19) -> 14985.83 | E19: =D19/C19 -> 0.33994131 | F19: =AVERAGEIFS(Dataset!$G$2:$G$201,Dataset!$C$2:$C$201,$A19) -> 0.11162791 | I19: CUST015 | J19: =INDEX(Dataset!$B$2:$B$201,MATCH(I19,Dataset!$A$2:$A$201,0)) -> Linda Taylor | K19: =COUNTIFS(Dataset!$A$2:$A$201,I19) -> 11 | L19: =SUMIFS(Dataset!$E$2:$E$201,Dataset!$A$2:$A$201,I19) -> 11611.06 | M19: =SUMIFS(Dataset!$I$2:$I$201,Dataset!$A$2:$A$201,I19) -> 4201.59 | N19: =RANK(L19,$L$5:$L$34)+COUNTIF($L$5:L19,L19)-1 -> 1 | O19: =IF(L19>=$R$4,"High Value","Standard") -> High Value | Q19: 7. TOP 10 CUSTOMERS BY TOTAL PURCHASE
A20: Total | B20: =SUM(B15:B19) -> 200 | C20: =SUM(C15:C19) -> 195217.76 | D20: =SUM(D15:D19) -> 68287.01 | E20: =D20/C20 -> 0.34979917 | F20: =AVERAGE(Dataset!$G$2:$G$201) -> 0.09725 | I20: CUST016 | J20: =INDEX(Dataset!$B$2:$B$201,MATCH(I20,Dataset!$A$2:$A$201,0)) -> Emma Wilson | K20: =COUNTIFS(Dataset!$A$2:$A$201,I20) -> 4 | L20: =SUMIFS(Dataset!$E$2:$E$201,Dataset!$A$2:$A$201,I20) -> 3369.17 | M20: =SUMIFS(Dataset!$I$2:$I$201,Dataset!$A$2:$A$201,I20) -> 1497.25 | N20: =RANK(L20,$L$5:$L$34)+COUNTIF($L$5:L20,L20)-1 -> 29 | O20: =IF(L20>=$R$4,"High Value","Standard") -> Standard | Q20: Rank | R20: Customer ID | S20: Name (first recorded) | T20: Total Sales | U20: Total Profit
I21: CUST017 | J21: =INDEX(Dataset!$B$2:$B$201,MATCH(I21,Dataset!$A$2:$A$201,0)) -> James Taylor | K21: =COUNTIFS(Dataset!$A$2:$A$201,I21) -> 4 | L21: =SUMIFS(Dataset!$E$2:$E$201,Dataset!$A$2:$A$201,I21) -> 3419.2 | M21: =SUMIFS(Dataset!$I$2:$I$201,Dataset!$A$2:$A$201,I21) -> 1257.21 | N21: =RANK(L21,$L$5:$L$34)+COUNTIF($L$5:L21,L21)-1 -> 28 | O21: =IF(L21>=$R$4,"High Value","Standard") -> Standard | Q21: 1 | R21: =INDEX($I$5:$I$34,MATCH($Q21,$N$5:$N$34,0)) -> CUST015 | S21: =INDEX($J$5:$J$34,MATCH($Q21,$N$5:$N$34,0)) -> Linda Taylor | T21: =INDEX($L$5:$L$34,MATCH($Q21,$N$5:$N$34,0)) -> 11611.06 | U21: =INDEX($M$5:$M$34,MATCH($Q21,$N$5:$N$34,0)) -> 4201.59
I22: CUST018 | J22: =INDEX(Dataset!$B$2:$B$201,MATCH(I22,Dataset!$A$2:$A$201,0)) -> Mary Jackson | K22: =COUNTIFS(Dataset!$A$2:$A$201,I22) -> 5 | L22: =SUMIFS(Dataset!$E$2:$E$201,Dataset!$A$2:$A$201,I22) -> 4951.89 | M22: =SUMIFS(Dataset!$I$2:$I$201,Dataset!$A$2:$A$201,I22) -> 1821.64 | N22: =RANK(L22,$L$5:$L$34)+COUNTIF($L$5:L22,L22)-1 -> 20 | O22: =IF(L22>=$R$4,"High Value","Standard") -> Standard | Q22: 2 | R22: =INDEX($I$5:$I$34,MATCH($Q22,$N$5:$N$34,0)) -> CUST028 | S22: =INDEX($J$5:$J$34,MATCH($Q22,$N$5:$N$34,0)) -> Linda Taylor | T22: =INDEX($L$5:$L$34,MATCH($Q22,$N$5:$N$34,0)) -> 10293.87 | U22: =INDEX($M$5:$M$34,MATCH($Q22,$N$5:$N$34,0)) -> 3541.02
A23: 3. PRODUCT CATEGORY SUMMARY | I23: CUST019 | J23: =INDEX(Dataset!$B$2:$B$201,MATCH(I23,Dataset!$A$2:$A$201,0)) -> James Davis | K23: =COUNTIFS(Dataset!$A$2:$A$201,I23) -> 5 | L23: =SUMIFS(Dataset!$E$2:$E$201,Dataset!$A$2:$A$201,I23) -> 4640.11 | M23: =SUMIFS(Dataset!$I$2:$I$201,Dataset!$A$2:$A$201,I23) -> 1721.12 | N23: =RANK(L23,$L$5:$L$34)+COUNTIF($L$5:L23,L23)-1 -> 21 | O23: =IF(L23>=$R$4,"High Value","Standard") -> Standard | Q23: 3 | R23: =INDEX($I$5:$I$34,MATCH($Q23,$N$5:$N$34,0)) -> CUST007 | S23: =INDEX($J$5:$J$34,MATCH($Q23,$N$5:$N$34,0)) -> Michael Anderson | T23: =INDEX($L$5:$L$34,MATCH($Q23,$N$5:$N$34,0)) -> 9941.88 | U23: =INDEX($M$5:$M$34,MATCH($Q23,$N$5:$N$34,0)) -> 3936.26
A24: Product Category | B24: Orders | C24: Sales | D24: Profit | E24: Profit Margin | F24: Avg Discount | I24: CUST020 | J24: =INDEX(Dataset!$B$2:$B$201,MATCH(I24,Dataset!$A$2:$A$201,0)) -> David Brown | K24: =COUNTIFS(Dataset!$A$2:$A$201,I24) -> 4 | L24: =SUMIFS(Dataset!$E$2:$E$201,Dataset!$A$2:$A$201,I24) -> 4413.71 | M24: =SUMIFS(Dataset!$I$2:$I$201,Dataset!$A$2:$A$201,I24) -> 1664.79 | N24: =RANK(L24,$L$5:$L$34)+COUNTIF($L$5:L24,L24)-1 -> 23 | O24: =IF(L24>=$R$4,"High Value","Standard") -> Standard | Q24: 4 | R24: =INDEX($I$5:$I$34,MATCH($Q24,$N$5:$N$34,0)) -> CUST008 | S24: =INDEX($J$5:$J$34,MATCH($Q24,$N$5:$N$34,0)) -> Robert Anderson | T24: =INDEX($L$5:$L$34,MATCH($Q24,$N$5:$N$34,0)) -> 9760.8 | U24: =INDEX($M$5:$M$34,MATCH($Q24,$N$5:$N$34,0)) -> 3442.48
A25: Books | B25: =COUNTIFS(Dataset!$D$2:$D$201,$A25) -> 49 | C25: =SUMIFS(Dataset!$E$2:$E$201,Dataset!$D$2:$D$201,$A25) -> 47002.46 | D25: =SUMIFS(Dataset!$I$2:$I$201,Dataset!$D$2:$D$201,$A25) -> 16901.63 | E25: =D25/C25 -> 0.35959033 | F25: =AVERAGEIFS(Dataset!$G$2:$G$201,Dataset!$D$2:$D$201,$A25) -> 0.10408163 | I25: CUST021 | J25: =INDEX(Dataset!$B$2:$B$201,MATCH(I25,Dataset!$A$2:$A$201,0)) -> Sarah Anderson | K25: =COUNTIFS(Dataset!$A$2:$A$201,I25) -> 8 | L25: =SUMIFS(Dataset!$E$2:$E$201,Dataset!$A$2:$A$201,I25) -> 8740.18 | M25: =SUMIFS(Dataset!$I$2:$I$201,Dataset!$A$2:$A$201,I25) -> 2848.62 | N25: =RANK(L25,$L$5:$L$34)+COUNTIF($L$5:L25,L25)-1 -> 6 | O25: =IF(L25>=$R$4,"High Value","Standard") -> High Value | Q25: 5 | R25: =INDEX($I$5:$I$34,MATCH($Q25,$N$5:$N$34,0)) -> CUST026 | S25: =INDEX($J$5:$J$34,MATCH($Q25,$N$5:$N$34,0)) -> Mary Davis | T25: =INDEX($L$5:$L$34,MATCH($Q25,$N$5:$N$34,0)) -> 9371.81 | U25: =INDEX($M$5:$M$34,MATCH($Q25,$N$5:$N$34,0)) -> 2922.02
A26: Clothing | B26: =COUNTIFS(Dataset!$D$2:$D$201,$A26) -> 41 | C26: =SUMIFS(Dataset!$E$2:$E$201,Dataset!$D$2:$D$201,$A26) -> 41927.59 | D26: =SUMIFS(Dataset!$I$2:$I$201,Dataset!$D$2:$D$201,$A26) -> 18784.49 | E26: =D26/C26 -> 0.44802217 | F26: =AVERAGEIFS(Dataset!$G$2:$G$201,Dataset!$D$2:$D$201,$A26) -> 0.098780488 | I26: CUST022 | J26: =INDEX(Dataset!$B$2:$B$201,MATCH(I26,Dataset!$A$2:$A$201,0)) -> Robert Anderson | K26: =COUNTIFS(Dataset!$A$2:$A$201,I26) -> 5 | L26: =SUMIFS(Dataset!$E$2:$E$201,Dataset!$A$2:$A$201,I26) -> 4418.28 | M26: =SUMIFS(Dataset!$I$2:$I$201,Dataset!$A$2:$A$201,I26) -> 1605.23 | N26: =RANK(L26,$L$5:$L$34)+COUNTIF($L$5:L26,L26)-1 -> 22 | O26: =IF(L26>=$R$4,"High Value","Standard") -> Standard | Q26: 6 | R26: =INDEX($I$5:$I$34,MATCH($Q26,$N$5:$N$34,0)) -> CUST021 | S26: =INDEX($J$5:$J$34,MATCH($Q26,$N$5:$N$34,0)) -> Sarah Anderson | T26: =INDEX($L$5:$L$34,MATCH($Q26,$N$5:$N$34,0)) -> 8740.18 | U26: =INDEX($M$5:$M$34,MATCH($Q26,$N$5:$N$34,0)) -> 2848.62
A27: Electronics | B27: =COUNTIFS(Dataset!$D$2:$D$201,$A27) -> 43 | C27: =SUMIFS(Dataset!$E$2:$E$201,Dataset!$D$2:$D$201,$A27) -> 41044 | D27: =SUMIFS(Dataset!$I$2:$I$201,Dataset!$D$2:$D$201,$A27) -> 9182.15 | E27: =D27/C27 -> 0.22371479 | F27: =AVERAGEIFS(Dataset!$G$2:$G$201,Dataset!$D$2:$D$201,$A27) -> 0.1 | I27: CUST023 | J27: =INDEX(Dataset!$B$2:$B$201,MATCH(I27,Dataset!$A$2:$A$201,0)) -> Robert Anderson | K27: =COUNTIFS(Dataset!$A$2:$A$201,I27) -> 7 | L27: =SUMIFS(Dataset!$E$2:$E$201,Dataset!$A$2:$A$201,I27) -> 5913.68 | M27: =SUMIFS(Dataset!$I$2:$I$201,Dataset!$A$2:$A$201,I27) -> 2198.62 | N27: =RANK(L27,$L$5:$L$34)+COUNTIF($L$5:L27,L27)-1 -> 18 | O27: =IF(L27>=$R$4,"High Value","Standard") -> Standard | Q27: 7 | R27: =INDEX($I$5:$I$34,MATCH($Q27,$N$5:$N$34,0)) -> CUST003 | S27: =INDEX($J$5:$J$34,MATCH($Q27,$N$5:$N$34,0)) -> Emma Davis | T27: =INDEX($L$5:$L$34,MATCH($Q27,$N$5:$N$34,0)) -> 8490.18 | U27: =INDEX($M$5:$M$34,MATCH($Q27,$N$5:$N$34,0)) -> 2652.75
A28: Furniture | B28: =COUNTIFS(Dataset!$D$2:$D$201,$A28) -> 36 | C28: =SUMIFS(Dataset!$E$2:$E$201,Dataset!$D$2:$D$201,$A28) -> 36612.89 | D28: =SUMIFS(Dataset!$I$2:$I$201,Dataset!$D$2:$D$201,$A28) -> 11579.14 | E28: =D28/C28 -> 0.31625856 | F28: =AVERAGEIFS(Dataset!$G$2:$G$201,Dataset!$D$2:$D$201,$A28) -> 0.097222222 | I28: CUST024 | J28: =INDEX(Dataset!$B$2:$B$201,MATCH(I28,Dataset!$A$2:$A$201,0)) -> David Brown | K28: =COUNTIFS(Dataset!$A$2:$A$201,I28) -> 7 | L28: =SUMIFS(Dataset!$E$2:$E$201,Dataset!$A$2:$A$201,I28) -> 7583.13 | M28: =SUMIFS(Dataset!$I$2:$I$201,Dataset!$A$2:$A$201,I28) -> 2492.1 | N28: =RANK(L28,$L$5:$L$34)+COUNTIF($L$5:L28,L28)-1 -> 11 | O28: =IF(L28>=$R$4,"High Value","Standard") -> Standard | Q28: 8 | R28: =INDEX($I$5:$I$34,MATCH($Q28,$N$5:$N$34,0)) -> CUST012 | S28: =INDEX($J$5:$J$34,MATCH($Q28,$N$5:$N$34,0)) -> Robert Anderson | T28: =INDEX($L$5:$L$34,MATCH($Q28,$N$5:$N$34,0)) -> 8339 | U28: =INDEX($M$5:$M$34,MATCH($Q28,$N$5:$N$34,0)) -> 2988.71
A29: Office Supplies | B29: =COUNTIFS(Dataset!$D$2:$D$201,$A29) -> 31 | C29: =SUMIFS(Dataset!$E$2:$E$201,Dataset!$D$2:$D$201,$A29) -> 28630.82 | D29: =SUMIFS(Dataset!$I$2:$I$201,Dataset!$D$2:$D$201,$A29) -> 11839.6 | E29: =D29/C29 -> 0.4135264 | F29: =AVERAGEIFS(Dataset!$G$2:$G$201,Dataset!$D$2:$D$201,$A29) -> 0.080645161 | I29: CUST025 | J29: =INDEX(Dataset!$B$2:$B$201,MATCH(I29,Dataset!$A$2:$A$201,0)) -> David Brown | K29: =COUNTIFS(Dataset!$A$2:$A$201,I29) -> 6 | L29: =SUMIFS(Dataset!$E$2:$E$201,Dataset!$A$2:$A$201,I29) -> 6716.52 | M29: =SUMIFS(Dataset!$I$2:$I$201,Dataset!$A$2:$A$201,I29) -> 2327.84 | N29: =RANK(L29,$L$5:$L$34)+COUNTIF($L$5:L29,L29)-1 -> 13 | O29: =IF(L29>=$R$4,"High Value","Standard") -> Standard | Q29: 9 | R29: =INDEX($I$5:$I$34,MATCH($Q29,$N$5:$N$34,0)) -> CUST030 | S29: =INDEX($J$5:$J$34,MATCH($Q29,$N$5:$N$34,0)) -> James Wilson | T29: =INDEX($L$5:$L$34,MATCH($Q29,$N$5:$N$34,0)) -> 7928.71 | U29: =INDEX($M$5:$M$34,MATCH($Q29,$N$5:$N$34,0)) -> 2965.48
A30: Total | B30: =SUM(B25:B29) -> 200 | C30: =SUM(C25:C29) -> 195217.76 | D30: =SUM(D25:D29) -> 68287.01 | E30: =D30/C30 -> 0.34979917 | F30: =AVERAGE(Dataset!$G$2:$G$201) -> 0.09725 | I30: CUST026 | J30: =INDEX(Dataset!$B$2:$B$201,MATCH(I30,Dataset!$A$2:$A$201,0)) -> Mary Davis | K30: =COUNTIFS(Dataset!$A$2:$A$201,I30) -> 9 | L30: =SUMIFS(Dataset!$E$2:$E$201,Dataset!$A$2:$A$201,I30) -> 9371.81 | M30: =SUMIFS(Dataset!$I$2:$I$201,Dataset!$A$2:$A$201,I30) -> 2922.02 | N30: =RANK(L30,$L$5:$L$34)+COUNTIF($L$5:L30,L30)-1 -> 5 | O30: =IF(L30>=$R$4,"High Value","Standard") -> High Value | Q30: 10 | R30: =INDEX($I$5:$I$34,MATCH($Q30,$N$5:$N$34,0)) -> CUST004 | S30: =INDEX($J$5:$J$34,MATCH($Q30,$N$5:$N$34,0)) -> Lisa Thomas | T30: =INDEX($L$5:$L$34,MATCH($Q30,$N$5:$N$34,0)) -> 7813.59 | U30: =INDEX($M$5:$M$34,MATCH($Q30,$N$5:$N$34,0)) -> 3211.82
I31: CUST027 | J31: =INDEX(Dataset!$B$2:$B$201,MATCH(I31,Dataset!$A$2:$A$201,0)) -> Emma Davis | K31: =COUNTIFS(Dataset!$A$2:$A$201,I31) -> 5 | L31: =SUMIFS(Dataset!$E$2:$E$201,Dataset!$A$2:$A$201,I31) -> 3906.04 | M31: =SUMIFS(Dataset!$I$2:$I$201,Dataset!$A$2:$A$201,I31) -> 1240.65 | N31: =RANK(L31,$L$5:$L$34)+COUNTIF($L$5:L31,L31)-1 -> 26 | O31: =IF(L31>=$R$4,"High Value","Standard") -> Standard
I32: CUST028 | J32: =INDEX(Dataset!$B$2:$B$201,MATCH(I32,Dataset!$A$2:$A$201,0)) -> Linda Taylor | K32: =COUNTIFS(Dataset!$A$2:$A$201,I32) -> 12 | L32: =SUMIFS(Dataset!$E$2:$E$201,Dataset!$A$2:$A$201,I32) -> 10293.87 | M32: =SUMIFS(Dataset!$I$2:$I$201,Dataset!$A$2:$A$201,I32) -> 3541.02 | N32: =RANK(L32,$L$5:$L$34)+COUNTIF($L$5:L32,L32)-1 -> 2 | O32: =IF(L32>=$R$4,"High Value","Standard") -> High Value
A33: 4. MONTHLY SALES TREND (with ▲▼ arrows via custom number format) | I33: CUST029 | J33: =INDEX(Dataset!$B$2:$B$201,MATCH(I33,Dataset!$A$2:$A$201,0)) -> David Smith | K33: =COUNTIFS(Dataset!$A$2:$A$201,I33) -> 7 | L33: =SUMIFS(Dataset!$E$2:$E$201,Dataset!$A$2:$A$201,I33) -> 5779.05 | M33: =SUMIFS(Dataset!$I$2:$I$201,Dataset!$A$2:$A$201,I33) -> 1611.66 | N33: =RANK(L33,$L$5:$L$34)+COUNTIF($L$5:L33,L33)-1 -> 19 | O33: =IF(L33>=$R$4,"High Value","Standard") -> Standard
A34: Month | B34: Sales | C34: Profit | D34: Orders | E34: MoM Change (▲▼) | F34: MoM Growth % (▲▼) | I34: CUST030 | J34: =INDEX(Dataset!$B$2:$B$201,MATCH(I34,Dataset!$A$2:$A$201,0)) -> James Wilson | K34: =COUNTIFS(Dataset!$A$2:$A$201,I34) -> 9 | L34: =SUMIFS(Dataset!$E$2:$E$201,Dataset!$A$2:$A$201,I34) -> 7928.71 | M34: =SUMIFS(Dataset!$I$2:$I$201,Dataset!$A$2:$A$201,I34) -> 2965.48 | N34: =RANK(L34,$L$5:$L$34)+COUNTIF($L$5:L34,L34)-1 -> 9 | O34: =IF(L34>=$R$4,"High Value","Standard") -> Standard
A35: =DATE(YEAR(MIN(Dataset!$H$2:$H$201)),MONTH(MIN(Dataset!$H$2:$H$201)),1) -> 45383 | B35: =SUMIFS(Dataset!$E$2:$E$201,Dataset!$P$2:$P$201,A35) -> 19029.96 | C35: =SUMIFS(Dataset!$I$2:$I$201,Dataset!$P$2:$P$201,A35) -> 6244.01 | D35: =COUNTIFS(Dataset!$P$2:$P$201,A35) -> 19 | E35: ="" | F35: ="" | I35: Total | K35: =SUM(K5:K34) -> 200 | L35: =SUM(L5:L34) -> 195217.76 | M35: =SUM(M5:M34) -> 68287.01
A36: =EDATE(A35,1) -> 45413 | B36: =SUMIFS(Dataset!$E$2:$E$201,Dataset!$P$2:$P$201,A36) -> 18507.34 | C36: =SUMIFS(Dataset!$I$2:$I$201,Dataset!$P$2:$P$201,A36) -> 6121.35 | D36: =COUNTIFS(Dataset!$P$2:$P$201,A36) -> 21 | E36: =B36-B35 -> -522.62 | F36: =(B36-B35)/B35 -> -0.027463011
A37: =EDATE(A36,1) -> 45444 | B37: =SUMIFS(Dataset!$E$2:$E$201,Dataset!$P$2:$P$201,A37) -> 20187.51 | C37: =SUMIFS(Dataset!$I$2:$I$201,Dataset!$P$2:$P$201,A37) -> 6918 | D37: =COUNTIFS(Dataset!$P$2:$P$201,A37) -> 20 | E37: =B37-B36 -> 1680.17 | F37: =(B37-B36)/B36 -> 0.090783981
A38: =EDATE(A37,1) -> 45474 | B38: =SUMIFS(Dataset!$E$2:$E$201,Dataset!$P$2:$P$201,A38) -> 11609.04 | C38: =SUMIFS(Dataset!$I$2:$I$201,Dataset!$P$2:$P$201,A38) -> 3743.85 | D38: =COUNTIFS(Dataset!$P$2:$P$201,A38) -> 12 | E38: =B38-B37 -> -8578.47 | F38: =(B38-B37)/B37 -> -0.42493948
A39: =EDATE(A38,1) -> 45505 | B39: =SUMIFS(Dataset!$E$2:$E$201,Dataset!$P$2:$P$201,A39) -> 10091.7 | C39: =SUMIFS(Dataset!$I$2:$I$201,Dataset!$P$2:$P$201,A39) -> 3302.84 | D39: =COUNTIFS(Dataset!$P$2:$P$201,A39) -> 10 | E39: =B39-B38 -> -1517.34 | F39: =(B39-B38)/B38 -> -0.13070331
A40: =EDATE(A39,1) -> 45536 | B40: =SUMIFS(Dataset!$E$2:$E$201,Dataset!$P$2:$P$201,A40) -> 20533.5 | C40: =SUMIFS(Dataset!$I$2:$I$201,Dataset!$P$2:$P$201,A40) -> 7457.52 | D40: =COUNTIFS(Dataset!$P$2:$P$201,A40) -> 20 | E40: =B40-B39 -> 10441.8 | F40: =(B40-B39)/B39 -> 1.0346919
A41: =EDATE(A40,1) -> 45566 | B41: =SUMIFS(Dataset!$E$2:$E$201,Dataset!$P$2:$P$201,A41) -> 14215.24 | C41: =SUMIFS(Dataset!$I$2:$I$201,Dataset!$P$2:$P$201,A41) -> 4861.7 | D41: =COUNTIFS(Dataset!$P$2:$P$201,A41) -> 14 | E41: =B41-B40 -> -6318.26 | F41: =(B41-B40)/B40 -> -0.30770497
A42: =EDATE(A41,1) -> 45597 | B42: =SUMIFS(Dataset!$E$2:$E$201,Dataset!$P$2:$P$201,A42) -> 20135.03 | C42: =SUMIFS(Dataset!$I$2:$I$201,Dataset!$P$2:$P$201,A42) -> 6814.88 | D42: =COUNTIFS(Dataset!$P$2:$P$201,A42) -> 20 | E42: =B42-B41 -> 5919.79 | F42: =(B42-B41)/B41 -> 0.41643968
A43: =EDATE(A42,1) -> 45627 | B43: =SUMIFS(Dataset!$E$2:$E$201,Dataset!$P$2:$P$201,A43) -> 11120.04 | C43: =SUMIFS(Dataset!$I$2:$I$201,Dataset!$P$2:$P$201,A43) -> 3549.99 | D43: =COUNTIFS(Dataset!$P$2:$P$201,A43) -> 11 | E43: =B43-B42 -> -9014.99 | F43: =(B43-B42)/B42 -> -0.44772667
A44: =EDATE(A43,1) -> 45658 | B44: =SUMIFS(Dataset!$E$2:$E$201,Dataset!$P$2:$P$201,A44) -> 14914.65 | C44: =SUMIFS(Dataset!$I$2:$I$201,Dataset!$P$2:$P$201,A44) -> 5763.4 | D44: =COUNTIFS(Dataset!$P$2:$P$201,A44) -> 16 | E44: =B44-B43 -> 3794.61 | F44: =(B44-B43)/B43 -> 0.34124068
A45: =EDATE(A44,1) -> 45689 | B45: =SUMIFS(Dataset!$E$2:$E$201,Dataset!$P$2:$P$201,A45) -> 14006.36 | C45: =SUMIFS(Dataset!$I$2:$I$201,Dataset!$P$2:$P$201,A45) -> 5039.23 | D45: =COUNTIFS(Dataset!$P$2:$P$201,A45) -> 14 | E45: =B45-B44 -> -908.29 | F45: =(B45-B44)/B44 -> -0.060899183
A46: =EDATE(A45,1) -> 45717 | B46: =SUMIFS(Dataset!$E$2:$E$201,Dataset!$P$2:$P$201,A46) -> 17655.22 | C46: =SUMIFS(Dataset!$I$2:$I$201,Dataset!$P$2:$P$201,A46) -> 7071.39 | D46: =COUNTIFS(Dataset!$P$2:$P$201,A46) -> 19 | E46: =B46-B45 -> 3648.86 | F46: =(B46-B45)/B45 -> 0.26051451
A47: =EDATE(A46,1) -> 45748 | B47: =SUMIFS(Dataset!$E$2:$E$201,Dataset!$P$2:$P$201,A47) -> 3212.17 | C47: =SUMIFS(Dataset!$I$2:$I$201,Dataset!$P$2:$P$201,A47) -> 1398.85 | D47: =COUNTIFS(Dataset!$P$2:$P$201,A47) -> 4 | E47: =B47-B46 -> -14443.05 | F47: =(B47-B46)/B46 -> -0.81806117
A48: Total | B48: =SUM(B35:B47) -> 195217.76 | C48: =SUM(C35:C47) -> 68287.01 | D48: =SUM(D35:D47) -> 200
A51: 8. NATIVE EXCEL PIVOTTABLES (right-click → Refresh, or Data → Refresh All)
A53: PivotTable 1 – Sum of Sales by Region (rows) × Product Category (columns)
A55: Sum of Sales | B55: Column Labels
A56: Row Labels | B56: Books | C56: Clothing | D56: Electronics | E56: Furniture | F56: Office Supplies | G56: Grand Total
A57: Central | B57: 11297.15 | C57: 12200.26 | D57: 6621.24 | E57: 4876.96 | F57: 8472.72 | G57: 43468.33
A58: East | B58: 11389.09 | C58: 2401.45 | D58: 2869.54 | E58: 7592.34 | F58: 8189.22 | G58: 32441.64
A59: North | B59: 8037.01 | C59: 8422.82 | D59: 8191.71 | E59: 6978.08 | F59: 3345.8 | G59: 34975.42
A60: South | B60: 9588.04 | C60: 8393.63 | D60: 11989.07 | E60: 7982.73 | F60: 2295.32 | G60: 40248.79
A61: West | B61: 6691.17 | C61: 10509.43 | D61: 11372.44 | E61: 9182.78 | F61: 6327.76 | G61: 44083.58
A62: Grand Total | B62: 47002.46 | C62: 41927.59 | D62: 41044 | E62: 36612.89 | F62: 28630.82 | G62: 195217.76
A64: PivotTable 2 – Sum of Sales and Profit by Product Category
B66: Values
A67: Row Labels | B67: Sum of Sales | C67: Sum of Profit
A68: Books | B68: 47002.46 | C68: 16901.63
A69: Clothing | B69: 41927.59 | C69: 18784.49
A70: Electronics | B70: 41044 | C70: 9182.15
A71: Furniture | B71: 36612.89 | C71: 11579.14
A72: Office Supplies | B72: 28630.82 | C72: 11839.6
A73: Grand Total | B73: 195217.76 | C73: 68287.01

Sheet Dashboard
B2: SALES ANALYTICS DASHBOARD
B3: ="Orders from "&TEXT(MIN(Dataset!$H$2:$H$201),"dd-mmm-yyyy")&" to "&TEXT(MAX(Dataset!$H$2:$H$201),"dd-mmm-yyyy")&" | "&TEXT(COUNT(Dataset!$E$2:$E$201),"0")&" orders | Refreshed "&TEXT(NOW(),"dd-mmm-yyyy hh:mm") -> Orders from 10-Apr-2024 to 07-Apr-2025 | 200 orders | Refreshed 09-Oct-2026 15:21
B5: TOTAL SALES | E5: TOTAL PROFIT | H5: PROFIT MARGIN | L5: TOTAL ORDERS | O5: AVG ORDER VALUE | R5: HIGH-VALUE CUSTOMERS
B6: ='Pivot Table'!C20 -> 195217.76 | E6: ='Pivot Table'!D20 -> 68287.01 | H6: ='Pivot Table'!E20 -> 0.34979917 | L6: ='Pivot Table'!B20 -> 200 | O6: ='Pivot Table'!C20/'Pivot Table'!B20 -> 976.0888 | R6: ='Pivot Table'!R5 -> 8
B8: AVG DISCOUNT | E8: LATEST MoM SALES GROWTH | H8: TOP REGION | L8: TOP PRODUCT CATEGORY | O8: PROFIT vs SALES R² | R8: TOP 10 CUSTOMER SHARE
B9: ='Pivot Table'!F20 -> 0.09725 | E9: ='Pivot Table'!F47 -> -0.81806117 | H9: =INDEX('Pivot Table'!A15:A19,MATCH(MAX('Pivot Table'!C15:C19),'Pivot Table'!C15:C19,0)) -> West | L9: =INDEX('Pivot Table'!A25:A29,MATCH(MAX('Pivot Table'!C25:C29),'Pivot Table'!C25:C29,0)) -> Books | O9: =Dataset!U65 -> 0.5981523 | R9: =SUM('Pivot Table'!T21:T30)/'Pivot Table'!C20 -> 0.47275965
B10: CHARTS – Bar · Pie · Line
B62: KEY INSIGHTS (Data Storytelling)
B63: ="1. Overview: "&TEXT('Pivot Table'!C20,"#,##0")&" in sales and "&TEXT('Pivot Table'!D20,"#,##0")&" in profit from "&'Pivot Table'!B20&" orders – an overall profit margin of "&TEXT('Pivot Table'!E20,"0.0%")&"." -> 1. Overview: 1,95,218 in sales and 68,287 in profit from 200 orders – an overall profit margin of 35.0%.
B64: ="2. Regions: "&INDEX('Pivot Table'!$A$15:$A$19,MATCH(MAX('Pivot Table'!$C$15:$C$19),'Pivot Table'!$C$15:$C$19,0))&" leads with "&TEXT(MAX('Pivot Table'!$C$15:$C$19),"#,##0")&" ("&TEXT(MAX('Pivot Table'!$C$15:$C$19)/'Pivot Table'!C20,"0.0%")&" of sales); "&INDEX('Pivot Table'!$A$15:$A$19,MATCH(MIN('Pivot Table'!$C$15:$C$19),'Pivot Table'!$C$15:$C$19,0))&" is lowest at "&TEXT(MIN('Pivot Table'!$C$15:$C$19),"#,##0")&"." -> 2. Regions: West leads with 44,084 (22.6% of sales); East is lowest at 32,442.
B65: ="3. Products: "&INDEX('Pivot Table'!$A$25:$A$29,MATCH(MAX('Pivot Table'!$C$25:$C$29),'Pivot Table'!$C$25:$C$29,0))&" is the top category ("&TEXT(MAX('Pivot Table'!$C$25:$C$29)/'Pivot Table'!C20,"0.0%")&" of sales); "&INDEX('Pivot Table'!$A$25:$A$29,MATCH(MIN('Pivot Table'!$C$25:$C$29),'Pivot Table'!$C$25:$C$29,0))&" contributes the least ("&TEXT(MIN('Pivot Table'!$C$25:$C$29)/'Pivot Table'!C20,"0.0%")&")." -> 3. Products: Books is the top category (24.1% of sales); Office Supplies contributes the least (14.7%).
B66: ="4. Trend: best month was "&TEXT(INDEX('Pivot Table'!A35:A47,MATCH(MAX('Pivot Table'!B35:B47),'Pivot Table'!B35:B47,0)),"mmm-yyyy")&" ("&TEXT(MAX('Pivot Table'!B35:B47),"#,##0")&"); weakest was "&TEXT(INDEX('Pivot Table'!A35:A47,MATCH(MIN('Pivot Table'!B35:B47),'Pivot Table'!B35:B47,0)),"mmm-yyyy")&" ("&TEXT(MIN('Pivot Table'!B35:B47),"#,##0")&"). The last month holds only part of a month, so its growth is understated." -> 4. Trend: best month was Sep-2024 (20,534); weakest was Apr-2025 (3,212). The last month holds only part of a month, so its growth is understated.
B67: ="5. Customers: the top 10 customers generate "&TEXT(SUM('Pivot Table'!T21:T30)/'Pivot Table'!C20,"0.0%")&" of sales, and "&'Pivot Table'!R5&" customers meet the high-value threshold of "&TEXT('Pivot Table'!R4,"#,##0")&"." -> 5. Customers: the top 10 customers generate 47.3% of sales, and 8 customers meet the high-value threshold of 8,236.
B68: ="6. Regression (ToolPak): every extra 1.00 of sales adds about "&TEXT(Dataset!U77,"0.00")&" of profit (R² = "&TEXT(Dataset!U65,"0.00")&"), so sales volume explains "&TEXT(Dataset!U65,"0%")&" of the variation in profit." -> 6. Regression (ToolPak): every extra 1.00 of sales adds about 0.35 of profit (R² = 0.60), so sales volume explains 60% of the variation in profit.
B69: ="7. What-if: a flat "&TEXT(Dataset!U3,"0%")&" discount would move total profit by "&TEXT(Dataset!W8,"#,##0;-#,##0")&" ("&TEXT(Dataset!X8,"0.0%;-0.0%")&"); hitting a profit target of "&TEXT(Dataset!U11,"#,##0")&" needs a discount of about "&IF(ISNUMBER(Dataset!U12),TEXT(Dataset!U12,"0.0%"),"– (not achievable)")&"." -> 7. What-if: a flat 10% discount would move total profit by 1,007 (1.5%); hitting a profit target of 80,000 needs a discount of about 5.1%.
